Workbook
Name _GoBack: Справочник!#REF!
Name Astra: #REF!
Name ESXi: #REF!
Name GGG: #REF!
Name HDD__Bronze: #REF!
Name HDD__Gold: #REF!
Name HDD__Iron: #REF!
Name HDD__Silver: #REF!
Name OC: #REF!
Name OEL: #REF!
Name PosEnt: #REF!
Name PosEnt_1С: #REF!
Name PosSt: #REF!
Name RHEL: #REF!
Name Service_File: #REF!
Name Service_Lin: #REF!
Name Service_NSX: #REF!
Name Service_Pos: #REF!
Name Service_SQL: #REF!
Name Service_Term: #REF!
Name Service_Win: #REF!
Name SQL: #REF!
Name USB: #REF!
Name VATS_BASE: #REF!
Name VATS_CLGATE: #REF!
Name VATS_ENH: #REF!
Name VATS_GATE: #REF!
Name VATS_STD: #REF!
Name vCPU: #REF!
Name vGPU: #REF!
Name vRAM: #REF!
Name WIN: #REF!
Name Разработка_АЗ_для_ЗнИ_на_подключение_площадки: #REF!
Name СРК: #REF!

Sheet Справочник
A1: Фамилия Имя Отчество | B1: Должность | C1: № Кабинета | D1: № Телефона | E1: № Корпоративный мобильный телефон | F1: Тип телефонной линии | G1: Звонок в TrueConf | H1: Звонок на № телефона с TrueConf | I1: ID TrueConf | J1: #телефона
A2: ИНФОРМАЦИЯ ДЛЯ СЛУЖЕБНОГО ПОЛЬЗОВАНИЯ | J2: =IF(D2=""," ",CONCATENATE("051",D2))
J3: =IF(D3=""," ",CONCATENATE("051",D3))
A4: РУКОВОДСТВО | J4: =IF(D4=""," ",CONCATENATE("051",D4))
J5: =IF(D5=""," ",CONCATENATE("051",D5))
A6: Баринов Александр Александрович | B6: Генеральный директор | D6: 46703 | J6: =IF(D6=""," ",CONCATENATE("051",D6)) -> 05146703
J7: =IF(D7=""," ",CONCATENATE("051",D7))
A8: Онищук Юлиана Валерьевна | B8: Помощник руководителя | D8: 46703 | E8: 9323230085 | G8: =IF(I8="","",HYPERLINK(CONCATENATE("trueconf:",I8),"Вызов по TrueConf")) -> Вызов по TrueConf | H8: =IF(J8=" ","",_xlfn.IFNA(HYPERLINK("Trueconf:#tel:"&J8,"Позвонить на № телефона"),"")) -> Позвонить на № телефона | I8: =IF(A8="","",IFERROR(VLOOKUP(A8,'ID TrueConf'!$P$2:$Q$4300,2,0),"")) -> onishchuk.yuv@tc7.pp.gazprom-neft.ru | J8: =IF(D8=""," ",CONCATENATE("051",D8)) -> 05146703
G9: =IF(I9="","",HYPERLINK(CONCATENATE("trueconf:",I9),"Вызов по TrueConf")) | H9: =IF(J9=" ","",_xlfn.IFNA(HYPERLINK("Trueconf:#tel:"&J9,"Позвонить на № телефона"),"")) | I9: =IF(A9="","",IFERROR(VLOOKUP(A9,'ID TrueConf'!$P$2:$Q$4300,2,0),"")) | J9: =IF(D9=""," ",CONCATENATE("051",D9))
B10: Операционный директор | D10: 46877 | G10: =IF(I10="","",HYPERLINK(CONCATENATE("trueconf:",I10),"Вызов по TrueConf")) | H10: =IF(J10=" ","",_xlfn.IFNA(HYPERLINK("Trueconf:#tel:"&J10,"Позвонить на № телефона"),"")) -> Позвонить на № телефона | I10: =IF(A10="","",IFERROR(VLOOKUP(A10,'ID TrueConf'!$P$2:$Q$4300,2,0),"")) | J10: =IF(D10=""," ",CONCATENATE("051",D10)) -> 05146877
A11: Бирюкова Мария Евгеньевна | B11: Специалист | D11: 43985 | E11: 982-573-98-47 | G11: =IF(I11="","",HYPERLINK(CONCATENATE("trueconf:",I11),"Вызов по TrueConf")) -> Вызов по TrueConf | H11: =IF(J11=" ","",_xlfn.IFNA(HYPERLINK("Trueconf:#tel:"&J11,"Позвонить на № телефона"),"")) -> Позвонить на № телефона | I11: =IF(A11="","",IFERROR(VLOOKUP(A11,'ID TrueConf'!$P$2:$Q$4300,2,0),"")) -> biryukova.me@tc20.pp.gazprom-neft.ru | J11: =IF(D11=""," ",CONCATENATE("051",D11)) -> 05143985
G12: =IF(I12="","",HYPERLINK(CONCATENATE("trueconf:",I12),"Вызов по TrueConf")) | H12: =IF(J12=" ","",_xlfn.IFNA(HYPERLINK("Trueconf:#tel:"&J12,"Позвонить на № телефона"),"")) | I12: =IF(A12="","",IFERROR(VLOOKUP(A12,'ID TrueConf'!$P$2:$Q$4300,2,0),"")) | J12: =IF(D12=""," ",CONCATENATE("051",D12))
A13: Доронин Евгений Васильевич | B13: Технический директор | D13: 46484 | G13: =IF(I13="","",HYPERLINK(CONCATENATE("trueconf:",I13),"Вызов по TrueConf")) -> Вызов по TrueConf | H13: =IF(J13=" ","",_xlfn.IFNA(HYPERLINK("Trueconf:#tel:"&J13,"Позвонить на № телефона"),"")) -> Позвонить на № телефона | I13: =IF(A13="","",IFERROR(VLOOKUP(A13,'ID TrueConf'!$P$2:$Q$4300,2,0),"")) -> doronin.ev@tc16.pp.gazprom-neft.ru | J13: =IF(D13=""," ",CONCATENATE("051",D13)) -> 05146484
A14: Шарапова Анна Вадимовна | B14: Ведущий специалист | D14: 46140 | G14: =IF(I14="","",HYPERLINK(CONCATENATE("trueconf:",I14),"Вызов по TrueConf")) -> Вызов по TrueConf | H14: =IF(J14=" ","",_xlfn.IFNA(HYPERLINK("Trueconf:#tel:"&J14,"Позвонить на № телефона"),"")) -> Позвонить на № телефона | I14: =IF(A14="","",IFERROR(VLOOKUP(A14,'ID TrueConf'!$P$2:$Q$4300,2,0),"")) -> sharapova.av@tc19.pp.gazprom-neft.ru | J14: =IF(D14=""," ",CONCATENATE("051",D14)) -> 05146140
G15: =IF(I15="","",HYPERLINK(CONCATENATE("trueconf:",I15),"Вызов по TrueConf")) | H15: =IF(J15=" ","",_xlfn.IFNA(HYPERLINK("Trueconf:#tel:"&J15,"Позвонить на № телефона"),"")) | I15: =IF(A15="","",IFERROR(VLOOKUP(A15,'ID TrueConf'!$P$2:$Q$4300,2,0),"")) | J15: =IF(D15=""," ",CONCATENATE("051",D15))
A16: Сейдалиев Тимур Фаррухович | B16: Заместитель генерального директора по экономике и финансам | D16: 46400 | G16: =IF(I16="","",HYPERLINK(CONCATENATE("trueconf:",I16),"Вызов по TrueConf")) -> Вызов по TrueConf | H16: =IF(J16=" ","",_xlfn.IFNA(HYPERLINK("Trueconf:#tel:"&J16,"Позвонить на № телефона"),"")) -> Позвонить на № телефона | I16: =IF(A16="","",IFERROR(VLOOKUP(A16,'ID TrueConf'!$P$2:$Q$4300,2,0),"")) -> seydaliev.tf@tc12.pp.gazprom-neft.ru | J16: =IF(D16=""," ",CONCATENATE("051",D16)) -> 05146400
G17: =IF(I17="","",HYPERLINK(CONCATENATE("trueconf:",I17),"Вызов по TrueConf")) | H17: =IF(J17=" ","",_xlfn.IFNA(HYPERLINK("Trueconf:#tel:"&J17,"Позвонить на № телефона"),"")) | I17: =IF(A17="","",IFERROR(VLOOKUP(A17,'ID TrueConf'!$P$2:$Q$4300,2,0),"")) | J17: =IF(D17=""," ",CONCATENATE("051",D17))
A18: Дубенец Андрей Викторович | B18: Заместитель генерального директора по обеспечению производства | D18: 46913 | G18: =IF(I18="","",HYPERLINK(CONCATENATE("trueconf:",I18),"Вызов по TrueConf")) -> Вызов по TrueConf | H18: =IF(J18=" ","",_xlfn.IFNA(HYPERLINK("Trueconf:#tel:"&J18,"Позвонить на № телефона"),"")) -> Позвонить на № телефона | I18: =IF(A18="","",IFERROR(VLOOKUP(A18,'ID TrueConf'!$P$2:$Q$4300,2,0),"")) -> dubenets.av@tc11.pp.gazprom-neft.ru | J18: =IF(D18=""," ",CONCATENATE("051",D18)) -> 05146913
G19: =IF(I19="","",HYPERLINK(CONCATENATE("trueconf:",I19),"Вызов по TrueConf")) | H19: =IF(J19=" ","",_xlfn.IFNA(HYPERLINK("Trueconf:#tel:"&J19,"Позвонить на № телефона"),"")) | I19: =IF(A19="","",IFERROR(VLOOKUP(A19,'ID TrueConf'!$P$2:$Q$4300,2,0),"")) | J19: =IF(D19=""," ",CONCATENATE("051",D19))
A20: Зимогляд Михаил Борисович | B20: Директор по вводу новых мощностей | D20: 46611 | G20: =IF(I20="","",HYPERLINK(CONCATENATE("trueconf:",I20),"Вызов по TrueConf")) | H20: =IF(J20=" ","",_xlfn.IFNA(HYPERLINK("Trueconf:#tel:"&J20,"Позвонить на № телефона"),"")) -> Позвонить на № телефона | I20: =IF(A20="","",IFERROR(VLOOKUP(A20,'ID TrueConf'!$P$2:$Q$4300,2,0),"")) | J20: =IF(D20=""," ",CONCATENATE("051",D20)) -> 05146611
G21: =IF(I21="","",HYPERLINK(CONCATENATE("trueconf:",I21),"Вызов по TrueConf")) | H21: =IF(J21=" ","",_xlfn.IFNA(HYPERLINK("Trueconf:#tel:"&J21,"Позвонить на № телефона"),"")) | I21: =IF(A21="","",IFERROR(VLOOKUP(A21,'ID TrueConf'!$P$2:$Q$4300,2,0),"")) | J21: =IF(D21=""," ",CONCATENATE("051",D21))
A22: Игитов Семен Михайлович | B22: Директор по геологии и разработке, концептуальному проектированию - главный геолог | D22: 46911 | G22: =IF(I22="","",HYPERLINK(CONCATENATE("trueconf:",I22),"Вызов по TrueConf")) -> Вызов по TrueConf | H22: =IF(J22=" ","",_xlfn.IFNA(HYPERLINK("Trueconf:#tel:"&J22,"Позвонить на № телефона"),"")) -> Позвонить на № телефона | I22: =IF(A22="","",IFERROR(VLOOKUP(A22,'ID TrueConf'!$P$2:$Q$4300,2,0),"")) -> igitov.sm@tc11.pp.gazprom-neft.ru | J22: =IF(D22=""," ",CONCATENATE("051",D22)) -> 05146911
G23: =IF(I23="","",HYPERLINK(CONCATENATE("trueconf:",I23),"Вызов по TrueConf")) | H23: =IF(J23=" ","",_xlfn.IFNA(HYPERLINK("Trueconf:#tel:"&J23,"Позвонить на № телефона"),"")) | I23: =IF(A23="","",IFERROR(VLOOKUP(A23,'ID TrueConf'!$P$2:$Q$4300,2,0),"")) | J23: =IF(D23=""," ",CONCATENATE("051",D23))
A24: Платоненкова Наталья Анатольевна | B24: Заместитель генерального директора по правовым и имущественным вопросам | D24: 46575 | G24: =IF(I24="","",HYPERLINK(CONCATENATE("trueconf:",I24),"Вызов по TrueConf")) -> Вызов по TrueConf | H24: =IF(J24=" ","",_xlfn.IFNA(HYPERLINK("Trueconf:#tel:"&J24,"Позвонить на № телефона"),"")) -> Позвонить на № телефона | I24: platonenkova.na@tc6.pp.gazprom-neft.ru | J24: =IF(D24=""," ",CONCATENATE("051",D24)) -> 05146575
G25: =IF(I25="","",HYPERLINK(CONCATENATE("trueconf:",I25),"Вызов по TrueConf")) | H25: =IF(J25=" ","",_xlfn.IFNA(HYPERLINK("Trueconf:#tel:"&J25,"Позвонить на № телефона"),"")) | I25: =IF(A25="","",IFERROR(VLOOKUP(A25,'ID TrueConf'!$P$2:$Q$4300,2,0),"")) | J25: =IF(D25=""," ",CONCATENATE("051",D25))
A26: Фазлирахманов Фархат Салихович | B26: Директор по капитальному строительству | D26: 41793 | G26: =IF(I26="","",HYPERLINK(CONCATENATE("trueconf:",I26),"Вызов по TrueConf")) -> Вызов по TrueConf | H26: =IF(J26=" ","",_xlfn.IFNA(HYPERLINK("Trueconf:#tel:"&J26,"Позвонить на № телефона"),"")) -> Позвонить на № телефона | I26: =IF(A26="","",IFERROR(VLOOKUP(A26,'ID TrueConf'!$P$2:$Q$4300,2,0),"")) -> fazlirakhmanov.fs@tc7.pp.gazprom-neft.ru | J26: =IF(D26=""," ",CONCATENATE("051",D26)) -> 05141793
A27: Стоянчук Наталья Юрьевна | B27: Специалист | D27: 41479 | G27: =IF(I27="","",HYPERLINK(CONCATENATE("trueconf:",I27),"Вызов по TrueConf")) -> Вызов по TrueConf | H27: =IF(J27=" ","",_xlfn.IFNA(HYPERLINK("Trueconf:#tel:"&J27,"Позвонить на № телефона"),"")) -> Позвонить на № телефона | I27: =IF(A27="","",IFERROR(VLOOKUP(A27,'ID TrueConf'!$P$2:$Q$4300,2,0),"")) -> stoyanchuk.nyu@tc13.pp.gazprom-neft.ru | J27: =IF(D27=""," ",CONCATENATE("051",D27)) -> 05141479
G28: =IF(I28="","",HYPERLINK(CONCATENATE("trueconf:",I28),"Вызов по TrueConf")) | H28: =IF(J28=" ","",_xlfn.IFNA(HYPERLINK("Trueconf:#tel:"&J28,"Позвонить на № телефона"),"")) | I28: =IF(A28="","",IFERROR(VLOOKUP(A28,'ID TrueConf'!$P$2:$Q$4300,2,0),"")) | J28: =IF(D28=""," ",CONCATENATE("051",D28))
A29: Ханипов Ильмир Фаилович | B29: Директор по перспективному развитию и управлению портфелем | D29: 46010 | G29: =IF(I29="","",HYPERLINK(CONCATENATE("trueconf:",I29),"Вызов по TrueConf")) -> Вызов по TrueConf | H29: =IF(J29=" ","",_xlfn.IFNA(HYPERLINK("Trueconf:#tel:"&J29,"Позвонить на № телефона"),"")) -> Позвонить на № телефона | I29: =IF(A29="","",IFERROR(VLOOKUP(A29,'ID TrueConf'!$P$2:$Q$4300,2,0),"")) -> khanipov.if@tc11.pp.gazprom-neft.ru | J29: =IF(D29=""," ",CONCATENATE("051",D29)) -> 05146010
G30: =IF(I30="","",HYPERLINK(CONCATENATE("trueconf:",I30),"Вызов по TrueConf")) | H30: =IF(J30=" ","",_xlfn.IFNA(HYPERLINK("Trueconf:#tel:"&J30,"Позвонить на № телефона"),"")) | I30: =IF(A30="","",IFERROR(VLOOKUP(A30,'ID TrueConf'!$P$2:$Q$4300,2,0),"")) | J30: =IF(D30=""," ",CONCATENATE("051",D30))
A31: Плотников Артем Витальевич | B31: Заместитель генерального директора по производственной и экологической безопасности | C31: АБК-1 | D31: 46501 | G31: =IF(I31="","",HYPERLINK(CONCATENATE("trueconf:",I31),"Вызов по TrueConf")) -> Вызов по TrueConf | H31: =IF(J31=" ","",_xlfn.IFNA(HYPERLINK("Trueconf:#tel:"&J31,"Позвонить на № телефона"),"")) -> Позвонить на № телефона | I31: =IF(A31="","",IFERROR(VLOOKUP(A31,'ID TrueConf'!$P$2:$Q$4300,2,0),"")) -> plotnikov.avit@tc11.pp.gazprom-neft.ru | J31: =IF(D31=""," ",CONCATENATE("051",D31)) -> 05146501
G32: =IF(I32="","",HYPERLINK(CONCATENATE("trueconf:",I32),"Вызов по TrueConf")) | H32: =IF(J32=" ","",_xlfn.IFNA(HYPERLINK("Trueconf:#tel:"&J32,"Позвонить на № телефона"),"")) | I32: =IF(A32="","",IFERROR(VLOOKUP(A32,'ID TrueConf'!$P$2:$Q$4300,2,0),"")) | J32: =IF(D32=""," ",CONCATENATE("051",D32))
G33: =IF(I33="","",HYPERLINK(CONCATENATE("trueconf:",I33),"Вызов по TrueConf")) | H33: =IF(J33=" ","",_xlfn.IFNA(HYPERLINK("Trueconf:#tel:"&J33,"Позвонить на № телефона"),"")) | I33: =IF(A33="","",IFERROR(VLOOKUP(A33,'ID TrueConf'!$P$2:$Q$4300,2,0),"")) | J33: =IF(D33=""," ",CONCATENATE("051",D33))
A34: Матвиенко Николай Николаевич | B34: Заместитель генерального директора по корпоративной защите | D34: 42187 | G34: =IF(I34="","",HYPERLINK(CONCATENATE("trueconf:",I34),"Вызов по TrueConf")) -> Вызов по TrueConf | H34: =IF(J34=" ","",_xlfn.IFNA(HYPERLINK("Trueconf:#tel:"&J34,"Позвонить на № телефона"),"")) -> Позвонить на № телефона | I34: =IF(A34="","",IFERROR(VLOOKUP(A34,'ID TrueConf'!$P$2:$Q$4300,2,0),"")) -> matvienko.nn@tc14.pp.gazprom-neft.ru | J34: =IF(D34=""," ",CONCATENATE("051",D34)) -> 05142187
G35: =IF(I35="","",HYPERLINK(CONCATENATE("trueconf:",I35),"Вызов по TrueConf")) | H35: =IF(J35=" ","",_xlfn.IFNA(HYPERLINK("Trueconf:#tel:"&J35,"Позвонить на № телефона"),"")) | I35: =IF(A35="","",IFERROR(VLOOKUP(A35,'ID TrueConf'!$P$2:$Q$4300,2,0),"")) | J35: =IF(D35=""," ",CONCATENATE("051",D35))
A36: Гордиенко Сергей Викторович | B36: Заместитель генерального директора по работе с персоналом и организационному развитию | C36: АБК-1, 2 этаж | D36: 46090 | G36: =IF(I36="","",HYPERLINK(CONCATENATE("trueconf:",I36),"Вызов по TrueConf")) -> Вызов по TrueConf | H36: =IF(J36=" ","",_xlfn.IFNA(HYPERLINK("Trueconf:#tel:"&J36,"Позвонить на № телефона"),"")) -> Позвонить на № телефона | I36: =IF(A36="","",IFERROR(VLOOKUP(A36,'ID TrueConf'!$P$2:$Q$4300,2,0),"")) -> gordienko.sv@tc12.pp.gazprom-neft.ru | J36: =IF(D36=""," ",CONCATENATE("051",D36)) -> 05146090
G37: =IF(I37="","",HYPERLINK(CONCATENATE("trueconf:",I37),"Вызов по TrueConf")) | H37: =IF(J37=" ","",_xlfn.IFNA(HYPERLINK("Trueconf:#tel:"&J37,"Позвонить на № телефона"),"")) | I37: =IF(A37="","",IFERROR(VLOOKUP(A37,'ID TrueConf'!$P$2:$Q$4300,2,0),"")) | J37: =IF(D37=""," ",CONCATENATE("051",D37))
B38: Директор по бизнес-трансформации | G38: =IF(I38="","",HYPERLINK(CONCATENATE("trueconf:",I38),"Вызов по TrueConf")) | H38: =IF(J38=" ","",_xlfn.IFNA(HYPERLINK("Trueconf:#tel:"&J38,"Позвонить на № телефона"),"")) | I38: =IF(A38="","",IFERROR(VLOOKUP(A38,'ID TrueConf'!$P$2:$Q$4300,2,0),"")) | J38: =IF(D38=""," ",CONCATENATE("051",D38))
G39: =IF(I39="","",HYPERLINK(CONCATENATE("trueconf:",I39),"Вызов по TrueConf")) | H39: =IF(J39=" ","",_xlfn.IFNA(HYPERLINK("Trueconf:#tel:"&J39,"Позвонить на № телефона"),"")) | I39: =IF(A39="","",IFERROR(VLOOKUP(A39,'ID TrueConf'!$P$2:$Q$4300,2,0),"")) | J39: =IF(D39=""," ",CONCATENATE("051",D39))
A40: Иванов Михаил Григорьевич | B40: Директор по газу | D40: 46664 | G40: =IF(I40="","",HYPERLINK(CONCATENATE("trueconf:",I40),"Вызов по TrueConf")) -> Вызов по TrueConf | H40: =IF(J40=" ","",_xlfn.IFNA(HYPERLINK("Trueconf:#tel:"&J40,"Позвонить на № телефона"),"")) -> Позвонить на № телефона | I40: =IF(A40="","",IFERROR(VLOOKUP(A40,'ID TrueConf'!$P$2:$Q$4300,2,0),"")) -> ivanov.mgr@tc2.pp.gazprom-neft.ru | J40: =IF(D40=""," ",CONCATENATE("051",D40)) -> 05146664
G41: =IF(I41="","",HYPERLINK(CONCATENATE("trueconf:",I41),"Вызов по TrueConf")) | H41: =IF(J41=" ","",_xlfn.IFNA(HYPERLINK("Trueconf:#tel:"&J41,"Позвонить на № телефона"),"")) | I41: =IF(A41="","",IFERROR(VLOOKUP(A41,'ID TrueConf'!$P$2:$Q$4300,2,0),"")) | J41: =IF(D41=""," ",CONCATENATE("051",D41))
A42: АППАРАТ ПРИ РУКОВОДСТВЕ | G42: =IF(I42="","",HYPERLINK(CONCATENATE("trueconf:",I42),"Вызов по TrueConf")) | H42: =IF(J42=" ","",_xlfn.IFNA(HYPERLINK("Trueconf:#tel:"&J42,"Позвонить на № телефона"),"")) | I42: =IF(A42="","",IFERROR(VLOOKUP(A42,'ID TrueConf'!$P$2:$Q$4300,2,0),"")) | J42: =IF(D42=""," ",CONCATENATE("051",D42))
G43: =IF(I43="","",HYPERLINK(CONCATENATE("trueconf:",I43),"Вызов по TrueConf")) | H43: =IF(J43=" ","",_xlfn.IFNA(HYPERLINK("Trueconf:#tel:"&J43,"Позвонить на № телефона"),"")) | I43: =IF(A43="","",IFERROR(VLOOKUP(A43,'ID TrueConf'!$P$2:$Q$4300,2,0),"")) | J43: =IF(D43=""," ",CONCATENATE("051",D43))
B44: Главный механик - руководитель по надежности и эффективности | C44: Офис «Асомкинский», ул.А.Кузьмина д.40 стр.13, 2 этаж, кабинет.207 | G44: =IF(I44="","",HYPERLINK(CONCATENATE("trueconf:",I44),"Вызов по TrueConf")) | H44: =IF(J44=" ","",_xlfn.IFNA(HYPERLINK("Trueconf:#tel:"&J44,"Позвонить на № телефона"),"")) | I44: =IF(A44="","",IFERROR(VLOOKUP(A44,'ID TrueConf'!$P$2:$Q$4300,2,0),"")) | J44: =IF(D44=""," ",CONCATENATE("051",D44))
A45: Беляев Сергей Александрович | B45: Главный метролог-руководитель по метрологии | C45: Офис «Асомкинский», ул.А.Кузьмина д.40 стр.13, 2 этаж, кабинет.202 | D45: 41074 | G45: =IF(I45="","",HYPERLINK(CONCATENATE("trueconf:",I45),"Вызов по TrueConf")) -> Вызов по TrueConf | H45: =IF(J45=" ","",_xlfn.IFNA(HYPERLINK("Trueconf:#tel:"&J45,"Позвонить на № телефона"),"")) -> Позвонить на № телефона | I45: =IF(A45="","",IFERROR(VLOOKUP(A45,'ID TrueConf'!$P$2:$Q$4300,2,0),"")) -> belyaev.sa@tc18.pp.gazprom-neft.ru | J45: =IF(D45=""," ",CONCATENATE("051",D45)) -> 05141074
A46: Шарапов Александр Сергеевич | B46: Главный теплотехник | C46: Офис «Асомкинский», ул.А.Кузьмина д.40 стр.13, 2 этаж, кабинет.212 | D46: 41269 | G46: =IF(I46="","",HYPERLINK(CONCATENATE("trueconf:",I46),"Вызов по TrueConf")) -> Вызов по TrueConf | H46: =IF(J46=" ","",_xlfn.IFNA(HYPERLINK("Trueconf:#tel:"&J46,"Позвонить на № телефона"),"")) -> Позвонить на № телефона | I46: =IF(A46="","",IFERROR(VLOOKUP(A46,'ID TrueConf'!$P$2:$Q$4300,2,0),"")) -> sharapov.aser@tc11.pp.gazprom-neft.ru | J46: =IF(D46=""," ",CONCATENATE("051",D46)) -> 05141269
A47: Кузнецов Михаил Юрьевич | B47: Главный энергетик-руководитель по энергоснабжению | D47: 42909 | G47: =IF(I47="","",HYPERLINK(CONCATENATE("trueconf:",I47),"Вызов по TrueConf")) | H47: =IF(J47=" ","",_xlfn.IFNA(HYPERLINK("Trueconf:#tel:"&J47,"Позвонить на № телефона"),"")) -> Позвонить на № телефона | I47: =IF(A47="","",IFERROR(VLOOKUP(A47,'ID TrueConf'!$P$2:$Q$4300,2,0),"")) | J47: =IF(D47=""," ",CONCATENATE("051",D47)) -> 05142909
A48: Соловей Денис Валерьевич | B48: Главный маркшейдер - начальник управления маркшейдерско-землеустроительных работ | D48: 47587 | G48: =IF(I48="","",HYPERLINK(CONCATENATE("trueconf:",I48),"Вызов по TrueConf")) -> Вызов по TrueConf | H48: =IF(J48=" ","",_xlfn.IFNA(HYPERLINK("Trueconf:#tel:"&J48,"Позвонить на № телефона"),"")) -> Позвонить на № телефона | I48: =IF(A48="","",IFERROR(VLOOKUP(A48,'ID TrueConf'!$P$2:$Q$4300,2,0),"")) -> solovey.dv@tc12.pp.gazprom-neft.ru | J48: =IF(D48=""," ",CONCATENATE("051",D48)) -> 05147587
A49: Захарченко Дмитрий Игоревич | B49: Руководитель программ по концептуальному проектированию и инжинирингу | C49: АБК-1, 4 этаж кабинет 431 | D49: 46439 | F49: Цифра | G49: =IF(I49="","",HYPERLINK(CONCATENATE("trueconf:",I49),"Вызов по TrueConf")) | H49: =IF(J49=" ","",_xlfn.IFNA(HYPERLINK("Trueconf:#tel:"&J49,"Позвонить на № телефона"),"")) -> Позвонить на № телефона
A50: Хропатый Виталий Викторович | B50: Руководитель программы развития проектной деятельности и риск- менеджмента | C50: АБК-1 4 этаж, (левое крыло) | F50: Цифра | G50: =IF(I50="","",HYPERLINK(CONCATENATE("trueconf:",I50),"Вызов по TrueConf")) -> Вызов по TrueConf | H50: =IF(J50=" ","",_xlfn.IFNA(HYPERLINK("Trueconf:#tel:"&J50,"Позвонить на № телефона"),"")) | I50: =IF(A50="","",IFERROR(VLOOKUP(A50,'ID TrueConf'!$P$2:$Q$4300,2,0),"")) -> khropatyy.vv@tc3.pp.gazprom-neft.ru | J50: =IF(D50=""," ",CONCATENATE("051",D50))
A51: Стороженко Роман Владимирович | B51: Руководитель направления развития проектной деятельности и риск- менеджмента | C51: АБК-1 4 этаж, (левое крыло) | D51: 41999 | F51: Цифра | G51: =IF(I51="","",HYPERLINK(CONCATENATE("trueconf:",I51),"Вызов по TrueConf")) -> Вызов по TrueConf | H51: =IF(J51=" ","",_xlfn.IFNA(HYPERLINK("Trueconf:#tel:"&J51,"Позвонить на № телефона"),"")) -> Позвонить на № телефона | I51: =IF(A51="","",IFERROR(VLOOKUP(A51,'ID TrueConf'!$P$2:$Q$4300,2,0),"")) -> storozhenko.rv@tc11.pp.gazprom-neft.ru | J51: =IF(D51=""," ",CONCATENATE("051",D51)) -> 05141999
A52: Дмитриев Александр Александрович | B52: Руководитель направления по энергоменеджменту | C52: АБК-1, 5 этаж (левое крыло) | G52: =IF(I52="","",HYPERLINK(CONCATENATE("trueconf:",I52),"Вызов по TrueConf")) -> Вызов по TrueConf | H52: =IF(J52=" ","",_xlfn.IFNA(HYPERLINK("Trueconf:#tel:"&J52,"Позвонить на № телефона"),"")) | I52: =IF(A52="","",IFERROR(VLOOKUP(A52,'ID TrueConf'!$P$2:$Q$4300,2,0),"")) -> dmitriev.aal@tc12.pp.gazprom-neft.ru | J52: =IF(D52=""," ",CONCATENATE("051",D52))
A53: Тауфик Юлия Олеговна | B53: Главный аудитор | C53: Офис «Аганский», ул. Нефтеразведочная, 2 каб. 318 | D53: 45800 | G53: =IF(I53="","",HYPERLINK(CONCATENATE("trueconf:",I53),"Вызов по TrueConf")) -> Вызов по TrueConf | H53: =IF(J53=" ","",_xlfn.IFNA(HYPERLINK("Trueconf:#tel:"&J53,"Позвонить на № телефона"),"")) -> Позвонить на № телефона | I53: =IF(A53="","",IFERROR(VLOOKUP(A53,'ID TrueConf'!$P$2:$Q$4300,2,0),"")) -> taufik.yuo@tc14.pp.gazprom-neft.ru | J53: =IF(D53=""," ",CONCATENATE("051",D53)) -> 05145800
A54: Пудовкин Денис Викторович | B54: Руководитель проектов по повышению производственной эффективности | C54: АБК-1, 2 этаж кабинет 214 | D54: 46197 | G54: =IF(I54="","",HYPERLINK(CONCATENATE("trueconf:",I54),"Вызов по TrueConf")) -> Вызов по TrueConf | H54: =IF(J54=" ","",_xlfn.IFNA(HYPERLINK("Trueconf:#tel:"&J54,"Позвонить на № телефона"),"")) -> Позвонить на № телефона | I54: =IF(A54="","",IFERROR(VLOOKUP(A54,'ID TrueConf'!$P$2:$Q$4300,2,0),"")) -> pudovkin.dv@tc11.pp.gazprom-neft.ru | J54: =IF(D54=""," ",CONCATENATE("051",D54)) -> 05146197
A55: Захарченко Дмитрий Игоревич | B55: Руководитель программ по концептуальному проектированию и инжинирингу | C55: АБК-1, 4 этаж кабинет 431 | D55: 46439 | F55: Цифра | G55: =IF(I55="","",HYPERLINK(CONCATENATE("trueconf:",I55),"Вызов по TrueConf")) -> Вызов по TrueConf | H55: =IF(J55=" ","",_xlfn.IFNA(HYPERLINK("Trueconf:#tel:"&J55,"Позвонить на № телефона"),"")) -> Позвонить на № телефона | I55: =IF(A55="","",IFERROR(VLOOKUP(A55,'ID TrueConf'!$P$2:$Q$4300,2,0),"")) -> zakharchenko.di@tc11.pp.gazprom-neft.ru | J55: =IF(D55=""," ",CONCATENATE("051",D55)) -> 05146439
A56: Олейников Виталий Сергеевич | B56: Руководитель проектов по новым технологиям | C56: АБК-1, 3 этаж, каб. 6 | D56: 43511 | G56: =IF(I56="","",HYPERLINK(CONCATENATE("trueconf:",I56),"Вызов по TrueConf")) -> Вызов по TrueConf | H56: =IF(J56=" ","",_xlfn.IFNA(HYPERLINK("Trueconf:#tel:"&J56,"Позвонить на № телефона"),"")) -> Позвонить на № телефона | I56: =IF(A56="","",IFERROR(VLOOKUP(A56,'ID TrueConf'!$P$2:$Q$4300,2,0),"")) -> oleynikov.vs@tc11.pp.gazprom-neft.ru | J56: =IF(D56=""," ",CONCATENATE("051",D56)) -> 05143511
G57: =IF(I57="","",HYPERLINK(CONCATENATE("trueconf:",I57),"Вызов по TrueConf")) | H57: =IF(J57=" ","",_xlfn.IFNA(HYPERLINK("Trueconf:#tel:"&J57,"Позвонить на № телефона"),"")) | I57: =IF(A57="","",IFERROR(VLOOKUP(A57,'ID TrueConf'!$P$2:$Q$4300,2,0),"")) | J57: =IF(D57=""," ",CONCATENATE("051",D57))
A58: АДМИНИСТРАТИВНЫЕ КОРПУСА | G58: =IF(I58="","",HYPERLINK(CONCATENATE("trueconf:",I58),"Вызов по TrueConf")) | H58: =IF(J58=" ","",_xlfn.IFNA(HYPERLINK("Trueconf:#tel:"&J58,"Позвонить на № телефона"),"")) | I58: =IF(A58="","",IFERROR(VLOOKUP(A58,'ID TrueConf'!$P$2:$Q$4300,2,0),"")) | J58: =IF(D58=""," ",CONCATENATE("051",D58))
G59: =IF(I59="","",HYPERLINK(CONCATENATE("trueconf:",I59),"Вызов по TrueConf")) | H59: =IF(J59=" ","",_xlfn.IFNA(HYPERLINK("Trueconf:#tel:"&J59,"Позвонить на № телефона"),"")) | I59: =IF(A59="","",IFERROR(VLOOKUP(A59,'ID TrueConf'!$P$2:$Q$4300,2,0),"")) | J59: =IF(D59=""," ",CONCATENATE("051",D59))
B60: Пропускной пункт АБК УКС | C60: ул.Пр.Победы, д.5 | D60: 41093 | G60: =IF(I60="","",HYPERLINK(CONCATENATE("trueconf:",I60),"Вызов по TrueConf")) | H60: =IF(J60=" ","",_xlfn.IFNA(HYPERLINK("Trueconf:#tel:"&J60,"Позвонить на № телефона"),"")) -> Позвонить на № телефона | I60: =IF(A60="","",IFERROR(VLOOKUP(A60,'ID TrueConf'!$P$2:$Q$4300,2,0),"")) | J60: =IF(D60=""," ",CONCATENATE("051",D60)) -> 05141093
B61: Пропускной пункт Офис «Покурский» | C61: ул.Западная д.10 | D61: 41953 | G61: =IF(I61="","",HYPERLINK(CONCATENATE("trueconf:",I61),"Вызов по TrueConf")) | H61: =IF(J61=" ","",_xlfn.IFNA(HYPERLINK("Trueconf:#tel:"&J61,"Позвонить на № телефона"),"")) -> Позвонить на № телефона | I61: =IF(A61="","",IFERROR(VLOOKUP(A61,'ID TrueConf'!$P$2:$Q$4300,2,0),"")) | J61: =IF(D61=""," ",CONCATENATE("051",D61)) -> 05141953
B62: Пропускной пункт Офис «Ватинский» | C62: ул.Новая, д.30А | D62: 42617 | G62: =IF(I62="","",HYPERLINK(CONCATENATE("trueconf:",I62),"Вызов по TrueConf")) | H62: =IF(J62=" ","",_xlfn.IFNA(HYPERLINK("Trueconf:#tel:"&J62,"Позвонить на № телефона"),"")) -> Позвонить на № телефона | I62: =IF(A62="","",IFERROR(VLOOKUP(A62,'ID TrueConf'!$P$2:$Q$4300,2,0),"")) | J62: =IF(D62=""," ",CONCATENATE("051",D62)) -> 05142617
B63: Пропускной пункт Офис «Баграс» | C63: ул.Театральный проезд, д.2 | D63: 43975 | G63: =IF(I63="","",HYPERLINK(CONCATENATE("trueconf:",I63),"Вызов по TrueConf")) | H63: =IF(J63=" ","",_xlfn.IFNA(HYPERLINK("Trueconf:#tel:"&J63,"Позвонить на № телефона"),"")) -> Позвонить на № телефона | I63: =IF(A63="","",IFERROR(VLOOKUP(A63,'ID TrueConf'!$P$2:$Q$4300,2,0),"")) | J63: =IF(D63=""," ",CONCATENATE("051",D63)) -> 05143975
B64: Пропускной пункт Офис «Аригольский» | C64: ул.А.Жагрина, д.21 | D64: 45656 | G64: =IF(I64="","",HYPERLINK(CONCATENATE("trueconf:",I64),"Вызов по TrueConf")) | H64: =IF(J64=" ","",_xlfn.IFNA(HYPERLINK("Trueconf:#tel:"&J64,"Позвонить на № телефона"),"")) -> Позвонить на № телефона | I64: =IF(A64="","",IFERROR(VLOOKUP(A64,'ID TrueConf'!$P$2:$Q$4300,2,0),"")) | J64: =IF(D64=""," ",CONCATENATE("051",D64)) -> 05145656
B65: Пропускной пункт Офис «Аганский» | C65: ул.Нефтеразведочная, д.2 | D65: 45877 | G65: =IF(I65="","",HYPERLINK(CONCATENATE("trueconf:",I65),"Вызов по TrueConf")) | H65: =IF(J65=" ","",_xlfn.IFNA(HYPERLINK("Trueconf:#tel:"&J65,"Позвонить на № телефона"),"")) -> Позвонить на № телефона | I65: =IF(A65="","",IFERROR(VLOOKUP(A65,'ID TrueConf'!$P$2:$Q$4300,2,0),"")) | J65: =IF(D65=""," ",CONCATENATE("051",D65)) -> 05145877
B66: Пропускной пункт на территорию Центра сервиса и ремонта | C66: ул.А.Кузьмина, д.34, стр.№1 | D66: 46130 | G66: =IF(I66="","",HYPERLINK(CONCATENATE("trueconf:",I66),"Вызов по TrueConf")) | H66: =IF(J66=" ","",_xlfn.IFNA(HYPERLINK("Trueconf:#tel:"&J66,"Позвонить на № телефона"),"")) -> Позвонить на № телефона | I66: =IF(A66="","",IFERROR(VLOOKUP(A66,'ID TrueConf'!$P$2:$Q$4300,2,0),"")) | J66: =IF(D66=""," ",CONCATENATE("051",D66)) -> 05146130
B67: Пропускной пункт АБК-1 | C67: ул.А.Кузьмина, д.51 | D67: 46199 | G67: =IF(I67="","",HYPERLINK(CONCATENATE("trueconf:",I67),"Вызов по TrueConf")) | H67: =IF(J67=" ","",_xlfn.IFNA(HYPERLINK("Trueconf:#tel:"&J67,"Позвонить на № телефона"),"")) -> Позвонить на № телефона | I67: =IF(A67="","",IFERROR(VLOOKUP(A67,'ID TrueConf'!$P$2:$Q$4300,2,0),"")) | J67: =IF(D67=""," ",CONCATENATE("051",D67)) -> 05146199
B68: Пропускной пункт СОК "Жемчужина" | C68: ул.И.Губкина, д.2 | D68: 46375 | G68: =IF(I68="","",HYPERLINK(CONCATENATE("trueconf:",I68),"Вызов по TrueConf")) | H68: =IF(J68=" ","",_xlfn.IFNA(HYPERLINK("Trueconf:#tel:"&J68,"Позвонить на № телефона"),"")) -> Позвонить на № телефона | I68: =IF(A68="","",IFERROR(VLOOKUP(A68,'ID TrueConf'!$P$2:$Q$4300,2,0),"")) | J68: =IF(D68=""," ",CONCATENATE("051",D68)) -> 05146375
B69: Пропускной пункт Офис «Асомкинский» | C69: ул.А.Кузьмина, д.40, стр.№13 | D69: 46884 | G69: =IF(I69="","",HYPERLINK(CONCATENATE("trueconf:",I69),"Вызов по TrueConf")) | H69: =IF(J69=" ","",_xlfn.IFNA(HYPERLINK("Trueconf:#tel:"&J69,"Позвонить на № телефона"),"")) -> Позвонить на № телефона | I69: =IF(A69="","",IFERROR(VLOOKUP(A69,'ID TrueConf'!$P$2:$Q$4300,2,0),"")) | J69: =IF(D69=""," ",CONCATENATE("051",D69)) -> 05146884
B70: Пропускной пункт на территорию ЦЛПАиУОП | C70: ул.А.Жагрина, д.8/4 | D70: 47838 | G70: =IF(I70="","",HYPERLINK(CONCATENATE("trueconf:",I70),"Вызов по TrueConf")) | H70: =IF(J70=" ","",_xlfn.IFNA(HYPERLINK("Trueconf:#tel:"&J70,"Позвонить на № телефона"),"")) -> Позвонить на № телефона | I70: =IF(A70="","",IFERROR(VLOOKUP(A70,'ID TrueConf'!$P$2:$Q$4300,2,0),"")) | J70: =IF(D70=""," ",CONCATENATE("051",D70)) -> 05147838
B71: Пропускной пункт Офис «Тайлаки» | C71: ул.А.Жагрина, д.20 | D71: 47887 | G71: =IF(I71="","",HYPERLINK(CONCATENATE("trueconf:",I71),"Вызов по TrueConf")) | H71: =IF(J71=" ","",_xlfn.IFNA(HYPERLINK("Trueconf:#tel:"&J71,"Позвонить на № телефона"),"")) -> Позвонить на № телефона | I71: =IF(A71="","",IFERROR(VLOOKUP(A71,'ID TrueConf'!$P$2:$Q$4300,2,0),"")) | J71: =IF(D71=""," ",CONCATENATE("051",D71)) -> 05147887
G72: =IF(I72="","",HYPERLINK(CONCATENATE("trueconf:",I72),"Вызов по TrueConf")) | H72: =IF(J72=" ","",_xlfn.IFNA(HYPERLINK("Trueconf:#tel:"&J72,"Позвонить на № телефона"),"")) | I72: =IF(A72="","",IFERROR(VLOOKUP(A72,'ID TrueConf'!$P$2:$Q$4300,2,0),"")) | J72: =IF(D72=""," ",CONCATENATE("051",D72))
A73: Группа по специальной работе | G73: =IF(I73="","",HYPERLINK(CONCATENATE("trueconf:",I73),"Вызов по TrueConf")) | H73: =IF(J73=" ","",_xlfn.IFNA(HYPERLINK("Trueconf:#tel:"&J73,"Позвонить на № телефона"),"")) | I73: =IF(A73="","",IFERROR(VLOOKUP(A73,'ID TrueConf'!$P$2:$Q$4300,2,0),"")) | J73: =IF(D73=""," ",CONCATENATE("051",D73))
A74: ул. Александра Жагрина, 20 | G74: =IF(I74="","",HYPERLINK(CONCATENATE("trueconf:",I74),"Вызов по TrueConf")) | H74: =IF(J74=" ","",_xlfn.IFNA(HYPERLINK("Trueconf:#tel:"&J74,"Позвонить на № телефона"),"")) | I74: =IF(A74="","",IFERROR(VLOOKUP(A74,'ID TrueConf'!$P$2:$Q$4300,2,0),"")) | J74: =IF(D74=""," ",CONCATENATE("051",D74))
A75: Лежнин Михаил Николаевич | B75: Руководитель группы | C75: 204 | D75: 47059 | F75: IP | G75: =IF(I75="","",HYPERLINK(CONCATENATE("trueconf:",I75),"Вызов по TrueConf")) -> Вызов по TrueConf | H75: =IF(J75=" ","",_xlfn.IFNA(HYPERLINK("Trueconf:#tel:"&J75,"Позвонить на № телефона"),"")) -> Позвонить на № телефона | I75: =IF(A75="","",IFERROR(VLOOKUP(A75,'ID TrueConf'!$P$2:$Q$4300,2,0),"")) -> lezhnin.mn@tc6.pp.gazprom-neft.ru | J75: =IF(D75=""," ",CONCATENATE("051",D75)) -> 05147059
A76: Капуста Алена Ивановна | B76: Ведущий специалист | C76: 205 | D76: 47991 | F76: Аналог | G76: =IF(I76="","",HYPERLINK(CONCATENATE("trueconf:",I76),"Вызов по TrueConf")) | H76: =IF(J76=" ","",_xlfn.IFNA(HYPERLINK("Trueconf:#tel:"&J76,"Позвонить на № телефона"),"")) -> Позвонить на № телефона | I76: =IF(A76="","",IFERROR(VLOOKUP(A76,'ID TrueConf'!$P$2:$Q$4300,2,0),"")) | J76: =IF(D76=""," ",CONCATENATE("051",D76)) -> 05147991
A77: Оганина Людмила Ярославовна | B77: Главный специалист | C77: 206 | D77: 47165 | F77: Аналог | G77: =IF(I77="","",HYPERLINK(CONCATENATE("trueconf:",I77),"Вызов по TrueConf")) | H77: =IF(J77=" ","",_xlfn.IFNA(HYPERLINK("Trueconf:#tel:"&J77,"Позвонить на № телефона"),"")) -> Позвонить на № телефона | I77: =IF(A77="","",IFERROR(VLOOKUP(A77,'ID TrueConf'!$P$2:$Q$4300,2,0),"")) | J77: =IF(D77=""," ",CONCATENATE("051",D77)) -> 05147165
A78: Щербакова Елена Юрьевна | B78: Специалист | C78: 206 | D78: 47943 | F78: Аналог | G78: =IF(I78="","",HYPERLINK(CONCATENATE("trueconf:",I78),"Вызов по TrueConf")) -> Вызов по TrueConf | H78: =IF(J78=" ","",_xlfn.IFNA(HYPERLINK("Trueconf:#tel:"&J78,"Позвонить на № телефона"),"")) -> Позвонить на № телефона | I78: oganina.lya@tc13.pp.gazprom-neft.ru | J78: =IF(D78=""," ",CONCATENATE("051",D78)) -> 05147943
G79: =IF(I79="","",HYPERLINK(CONCATENATE("trueconf:",I79),"Вызов по TrueConf")) | H79: =IF(J79=" ","",_xlfn.IFNA(HYPERLINK("Trueconf:#tel:"&J79,"Позвонить на № телефона"),"")) | I79: =IF(A79="","",IFERROR(VLOOKUP(A79,'ID TrueConf'!$P$2:$Q$4300,2,0),"")) | J79: =IF(D79=""," ",CONCATENATE("051",D79))
A80: УПРАВЛЕНИЕ КОРПОРАТИВНЫХ КОММУНИКАЦИЙ | G80: =IF(I80="","",HYPERLINK(CONCATENATE("trueconf:",I80),"Вызов по TrueConf")) | H80: =IF(J80=" ","",_xlfn.IFNA(HYPERLINK("Trueconf:#tel:"&J80,"Позвонить на № телефона"),"")) | I80: =IF(A80="","",IFERROR(VLOOKUP(A80,'ID TrueConf'!$P$2:$Q$4300,2,0),"")) | J80: =IF(D80=""," ",CONCATENATE("051",D80))
A81: ул. А.М. Кузьмина, 51 | G81: =IF(I81="","",HYPERLINK(CONCATENATE("trueconf:",I81),"Вызов по TrueConf")) | H81: =IF(J81=" ","",_xlfn.IFNA(HYPERLINK("Trueconf:#tel:"&J81,"Позвонить на № телефона"),"")) | I81: =IF(A81="","",IFERROR(VLOOKUP(A81,'ID TrueConf'!$P$2:$Q$4300,2,0),"")) | J81: =IF(D81=""," ",CONCATENATE("051",D81))
A82: Электронный адрес | E82: ukk-snmng@gazprom-neft.ru | G82: =IF(I82="","",HYPERLINK(CONCATENATE("trueconf:",I82),"Вызов по TrueConf")) | H82: =IF(J82=" ","",_xlfn.IFNA(HYPERLINK("Trueconf:#tel:"&J82,"Позвонить на № телефона"),"")) | I82: =IF(A82="","",IFERROR(VLOOKUP(A82,'ID TrueConf'!$P$2:$Q$4300,2,0),"")) | J82: =IF(D82=""," ",CONCATENATE("051",D82))
B83: Начальник управления | G83: =IF(I83="","",HYPERLINK(CONCATENATE("trueconf:",I83),"Вызов по TrueConf")) | H83: =IF(J83=" ","",_xlfn.IFNA(HYPERLINK("Trueconf:#tel:"&J83,"Позвонить на № телефона"),"")) | I83: =IF(A83="","",IFERROR(VLOOKUP(A83,'ID TrueConf'!$P$2:$Q$4300,2,0),"")) | J83: =IF(D83=""," ",CONCATENATE("051",D83))
A84: Юшин Дмитрий Михайлович | B84: Руководитель направления | D84: 49299 | G84: =IF(I84="","",HYPERLINK(CONCATENATE("trueconf:",I84),"Вызов по TrueConf")) -> Вызов по TrueConf | H84: =IF(J84=" ","",_xlfn.IFNA(HYPERLINK("Trueconf:#tel:"&J84,"Позвонить на № телефона"),"")) -> Позвонить на № телефона | I84: =IF(A84="","",IFERROR(VLOOKUP(A84,'ID TrueConf'!$P$2:$Q$4300,2,0),"")) -> iushin.dm@tc11.pp.gazprom-neft.ru | J84: =IF(D84=""," ",CONCATENATE("051",D84)) -> 05149299
A85: Кулешова Алена Александровна | B85: Руководитель направления по взаимодействию с КМНС | C85: ул. Александра Жагрина, д 21, каб. №108 | D85: 42938 | G85: =IF(I85="","",HYPERLINK(CONCATENATE("trueconf:",I85),"Вызов по TrueConf")) -> Вызов по TrueConf | H85: =IF(J85=" ","",_xlfn.IFNA(HYPERLINK("Trueconf:#tel:"&J85,"Позвонить на № телефона"),"")) -> Позвонить на № телефона | I85: kuleshova.aa@tc11.pp.gazprom-neft.ru | J85: =IF(D85=""," ",CONCATENATE("051",D85)) -> 05142938
A86: Белан Светлана Ивановна | B86: Главный специалист | E86: =VLOOKUP(A86,[1]Лист2!$A$3:$B$300,2,0) -> 9227875613 | G86: =IF(I86="","",HYPERLINK(CONCATENATE("trueconf:",I86),"Вызов по TrueConf")) -> Вызов по TrueConf | H86: =IF(J86=" ","",_xlfn.IFNA(HYPERLINK("Trueconf:#tel:"&J86,"Позвонить на № телефона"),"")) | I86: belan.si@tc14.pp.gazprom-neft.ru | J86: =IF(D86=""," ",CONCATENATE("051",D86))
A87: Ириневич Светлана Викторовна | B87: Главный специалист | D87: 47472 | G87: =IF(I87="","",HYPERLINK(CONCATENATE("trueconf:",I87),"Вызов по TrueConf")) -> Вызов по TrueConf | H87: =IF(J87=" ","",_xlfn.IFNA(HYPERLINK("Trueconf:#tel:"&J87,"Позвонить на № телефона"),"")) -> Позвонить на № телефона | I87: =IF(A87="","",IFERROR(VLOOKUP(A87,'ID TrueConf'!$P$2:$Q$4300,2,0),"")) -> irinevich.svi@tc20.pp.gazprom-neft.ru | J87: =IF(D87=""," ",CONCATENATE("051",D87)) -> 05147472
G88: =IF(I88="","",HYPERLINK(CONCATENATE("trueconf:",I88),"Вызов по TrueConf")) | H88: =IF(J88=" ","",_xlfn.IFNA(HYPERLINK("Trueconf:#tel:"&J88,"Позвонить на № телефона"),"")) | I88: =IF(A88="","",IFERROR(VLOOKUP(A88,'ID TrueConf'!$P$2:$Q$4300,2,0),"")) | J88: =IF(D88=""," ",CONCATENATE("051",D88))
A89: УПРАВЛЕНИЕ ИМУЩЕСТВЕННЫХ ОТНОШЕНИЙ (УИО) | G89: =IF(I89="","",HYPERLINK(CONCATENATE("trueconf:",I89),"Вызов по TrueConf")) | H89: =IF(J89=" ","",_xlfn.IFNA(HYPERLINK("Trueconf:#tel:"&J89,"Позвонить на № телефона"),"")) | I89: =IF(A89="","",IFERROR(VLOOKUP(A89,'ID TrueConf'!$P$2:$Q$4300,2,0),"")) | J89: =IF(D89=""," ",CONCATENATE("051",D89))
A90: Офис "Аганский" ул. Нефтеразведочная, 2 | G90: =IF(I90="","",HYPERLINK(CONCATENATE("trueconf:",I90),"Вызов по TrueConf")) | H90: =IF(J90=" ","",_xlfn.IFNA(HYPERLINK("Trueconf:#tel:"&J90,"Позвонить на № телефона"),"")) | I90: =IF(A90="","",IFERROR(VLOOKUP(A90,'ID TrueConf'!$P$2:$Q$4300,2,0),"")) | J90: =IF(D90=""," ",CONCATENATE("051",D90))
A91: Электронный адрес | E91: uio-snmng@gazprom-neft.ru | G91: =IF(I91="","",HYPERLINK(CONCATENATE("trueconf:",I91),"Вызов по TrueConf")) | H91: =IF(J91=" ","",_xlfn.IFNA(HYPERLINK("Trueconf:#tel:"&J91,"Позвонить на № телефона"),"")) | I91: =IF(A91="","",IFERROR(VLOOKUP(A91,'ID TrueConf'!$P$2:$Q$4300,2,0),"")) | J91: =IF(D91=""," ",CONCATENATE("051",D91))
A92: Неверов Юрий Владимирович | B92: Начальник управления | C92: 207 | D92: 46488 | F92: Цифра | G92: =IF(I92="","",HYPERLINK(CONCATENATE("trueconf:",I92),"Вызов по TrueConf")) -> Вызов по TrueConf | H92: =IF(J92=" ","",_xlfn.IFNA(HYPERLINK("Trueconf:#tel:"&J92,"Позвонить на № телефона"),"")) -> Позвонить на № телефона | I92: =IF(A92="","",IFERROR(VLOOKUP(A92,'ID TrueConf'!$P$2:$Q$4300,2,0),"")) -> neverov.yuv@tc11.pp.gazprom-neft.ru | J92: =IF(D92=""," ",CONCATENATE("051",D92)) -> 05146488
A93: Отдел управления имуществом (ОУИ) | G93: =IF(I93="","",HYPERLINK(CONCATENATE("trueconf:",I93),"Вызов по TrueConf")) | H93: =IF(J93=" ","",_xlfn.IFNA(HYPERLINK("Trueconf:#tel:"&J93,"Позвонить на № телефона"),"")) | I93: =IF(A93="","",IFERROR(VLOOKUP(A93,'ID TrueConf'!$P$2:$Q$4300,2,0),"")) | J93: =IF(D93=""," ",CONCATENATE("051",D93))
A94: Марченко Илья Александрович | B94: Начальник отдела | C94: 209 | D94: 46244 | F94: Цифра | G94: =IF(I94="","",HYPERLINK(CONCATENATE("trueconf:",I94),"Вызов по TrueConf")) -> Вызов по TrueConf | H94: =IF(J94=" ","",_xlfn.IFNA(HYPERLINK("Trueconf:#tel:"&J94,"Позвонить на № телефона"),"")) -> Позвонить на № телефона | I94: =IF(A94="","",IFERROR(VLOOKUP(A94,'ID TrueConf'!$P$2:$Q$4300,2,0),"")) -> marchenko.ia@tc12.pp.gazprom-neft.ru | J94: =IF(D94=""," ",CONCATENATE("051",D94)) -> 05146244
A95: Мельникова Татьяна Геннадьевна | B95: Главный специалист | C95: 209 | D95: 49248 | F95: Аналог | G95: =IF(I95="","",HYPERLINK(CONCATENATE("trueconf:",I95),"Вызов по TrueConf")) -> Вызов по TrueConf | H95: =IF(J95=" ","",_xlfn.IFNA(HYPERLINK("Trueconf:#tel:"&J95,"Позвонить на № телефона"),"")) -> Позвонить на № телефона | I95: =IF(A95="","",IFERROR(VLOOKUP(A95,'ID TrueConf'!$P$2:$Q$4300,2,0),"")) -> melnikova.tg@tc7.pp.gazprom-neft.ru | J95: =IF(D95=""," ",CONCATENATE("051",D95)) -> 05149248
A96: Николаева Анжелика Федоровна | B96: Главный специалист | C96: 209 | D96: 46229 | F96: Аналог | G96: =IF(I96="","",HYPERLINK(CONCATENATE("trueconf:",I96),"Вызов по TrueConf")) -> Вызов по TrueConf | H96: =IF(J96=" ","",_xlfn.IFNA(HYPERLINK("Trueconf:#tel:"&J96,"Позвонить на № телефона"),"")) -> Позвонить на № телефона | I96: =IF(A96="","",IFERROR(VLOOKUP(A96,'ID TrueConf'!$P$2:$Q$4300,2,0),"")) -> nikolaeva.afe@tc11.pp.gazprom-neft.ru | J96: =IF(D96=""," ",CONCATENATE("051",D96)) -> 05146229
A97: Тукаева Оксана Анатольевна | B97: Главный специалист | C97: 209 | D97: 49230 | F97: Аналог | G97: =IF(I97="","",HYPERLINK(CONCATENATE("trueconf:",I97),"Вызов по TrueConf")) -> Вызов по TrueConf | H97: =IF(J97=" ","",_xlfn.IFNA(HYPERLINK("Trueconf:#tel:"&J97,"Позвонить на № телефона"),"")) -> Позвонить на № телефона | I97: =IF(A97="","",IFERROR(VLOOKUP(A97,'ID TrueConf'!$P$2:$Q$4300,2,0),"")) -> tukaeva.oa@tc11.pp.gazprom-neft.ru | J97: =IF(D97=""," ",CONCATENATE("051",D97)) -> 05149230
A98: Колосков Владимир Сергеевич | B98: Ведущий специалист | C98: 209 | F98: Аналог | G98: =IF(I98="","",HYPERLINK(CONCATENATE("trueconf:",I98),"Вызов по TrueConf")) -> Вызов по TrueConf | H98: =IF(J98=" ","",_xlfn.IFNA(HYPERLINK("Trueconf:#tel:"&J98,"Позвонить на № телефона"),"")) | I98: =IF(A98="","",IFERROR(VLOOKUP(A98,'ID TrueConf'!$P$2:$Q$4300,2,0),"")) -> koloskov.vs@tc19.pp.gazprom-neft.ru | J98: =IF(D98=""," ",CONCATENATE("051",D98))
A99: Писковацкая Ирина Раузатовна | B99: Ведущий специалист | C99: 209 | D99: 49241 | G99: =IF(I99="","",HYPERLINK(CONCATENATE("trueconf:",I99),"Вызов по TrueConf")) -> Вызов по TrueConf | H99: =IF(J99=" ","",_xlfn.IFNA(HYPERLINK("Trueconf:#tel:"&J99,"Позвонить на № телефона"),"")) -> Позвонить на № телефона | I99: koloskov.vs@tc19.pp.gazprom-neft.ru
I100: =IF(A100="","",IFERROR(VLOOKUP(A100,'ID TrueConf'!$P$2:$Q$4300,2,0),"")) | J100: =IF(D100=""," ",CONCATENATE("051",D100))
...

Sheet ID TrueConf
A1: № | B1: Тип объекта обслуживания | C1: Объект обслуживания | D1: Период | E1: Компонент | F1: Тариф | G1: Количество | H1: Дней потребления | I1: Начислено руб. (без НДС) | J1: Целевой SLA, % | K1: Фактический SLA, % | L1: Скидка по SLA, руб. (без НДС) | M1: Итого со скидкой, руб. (без НДС) (индикативно) | N1: Комментарий заказчика | O1: Комментарий исполнителя | P1: Комментарий | Q1: Атрибут | R1: сверка
A2: 1 | B2: Учетная запись | C2: gaysin.rr | D2: ТЕКУЩИЙ ПЕРИОД | E2: Учетная запись ВКС | F2: 1249.63 | G2: 1 | H2: 28 | I2: 1249.63 | J2: 96.84 | K2: 100 | L2: 0 | M2: 1249.63 | P2: Гайсин Руслан Рамилевич | Q2: gaysin.rr@tc12.pp.gazprom-neft.ru | R2: =VLOOKUP(Таблица3[[#This Row],[Комментарий]],Справочник!$A$6:$B$4224,2,0) -> Начальник отдела
A3: 2 | B3: Учетная запись | C3: letko.ii | D3: ТЕКУЩИЙ ПЕРИОД | E3: Учетная запись ВКС | F3: 1249.63 | G3: 1 | H3: 28 | I3: 1249.63 | J3: 96.84 | K3: 100 | L3: 0 | M3: 1249.63 | P3: Летко Иван Иванович | Q3: letko.ii@tc11.pp.gazprom-neft.ru | R3: =VLOOKUP(Таблица3[[#This Row],[Комментарий]],Справочник!$A$6:$B$4224,2,0) -> Начальник управления
A4: 3 | B4: Учетная запись | C4: abdeev.am | D4: ТЕКУЩИЙ ПЕРИОД | E4: Учетная запись ВКС | F4: 1249.63 | G4: 1 | H4: 28 | I4: 1249.63 | J4: 96.84 | K4: 100 | L4: 0 | M4: 1249.63 | P4: Абдеев Алик Мидхатович | Q4: abdeev.am@tc11.pp.gazprom-neft.ru | R4: =VLOOKUP(Таблица3[[#This Row],[Комментарий]],Справочник!$A$6:$B$4224,2,0) -> Руководитель направления по сопровождению гидроразрыва пластов
A5: 4 | B5: Учетная запись | C5: abdullin.tr | D5: ТЕКУЩИЙ ПЕРИОД | E5: Учетная запись ВКС | F5: 1249.63 | G5: 1 | H5: 28 | I5: 1249.63 | J5: 96.84 | K5: 100 | L5: 0 | M5: 1249.63 | P5: Абдуллин Тагир Рафаэлевич | Q5: abdullin.tr@tc15.pp.gazprom-neft.ru | R5: =VLOOKUP(Таблица3[[#This Row],[Комментарий]],Справочник!$A$6:$B$4224,2,0) -> Ведущий инженер | S5: =[6]!ExtractElement(Таблица3[[#This Row],[Комментарий]],1," ") -> #NAME? | T5: =Таблица3[[#This Row],[Комментарий]] -> Абдуллин Тагир Рафаэлевич
A6: 5 | B6: Учетная запись | C6: abzalova.gr | D6: ТЕКУЩИЙ ПЕРИОД | E6: Учетная запись ВКС | F6: 1249.63 | G6: 1 | H6: 28 | I6: 1249.63 | J6: 96.84 | K6: 100 | L6: 0 | M6: 1249.63 | P6: Абзалова Гульшат Радисовна | Q6: abzalova.gr@tc15.pp.gazprom-neft.ru | R6: =VLOOKUP(Таблица3[[#This Row],[Комментарий]],Справочник!$A$6:$B$4224,2,0) -> Заведующий лабораторией
A7: 6 | B7: Учетная запись | C7: abileva.nm | D7: ТЕКУЩИЙ ПЕРИОД | E7: Учетная запись ВКС | F7: 1249.63 | G7: 1 | H7: 28 | I7: 1249.63 | J7: 96.84 | K7: 100 | L7: 0 | M7: 1249.63 | P7: Абилева Наиля Малдыбаевна | Q7: abileva.nm@tc11.pp.gazprom-neft.ru | R7: =VLOOKUP(Таблица3[[#This Row],[Комментарий]],Справочник!$A$6:$B$4224,2,0) -> РН по капитальному строительству, капитальному ремонту
A8: 7 | B8: Учетная запись | C8: avkhadiev.da | D8: ТЕКУЩИЙ ПЕРИОД | E8: Учетная запись ВКС | F8: 1249.63 | G8: 1 | H8: 28 | I8: 1249.63 | J8: 96.84 | K8: 100 | L8: 0 | M8: 1249.63 | P8: Авхадиев Денис Анварович | Q8: avkhadiev.da@tc15.pp.gazprom-neft.ru | R8: =VLOOKUP(Таблица3[[#This Row],[Комментарий]],Справочник!$A$6:$B$4224,2,0) -> Главный специалист
A9: 8 | B9: Учетная запись | C9: agafonova.da | D9: ТЕКУЩИЙ ПЕРИОД | E9: Учетная запись ВКС | F9: 1249.63 | G9: 1 | H9: 28 | I9: 1249.63 | J9: 96.84 | K9: 100 | L9: 0 | M9: 1249.63 | P9: Агафонова Дарья Анатольевна | Q9: agafonova.da@tc6.pp.gazprom-neft.ru | R9: =VLOOKUP(Таблица3[[#This Row],[Комментарий]],Справочник!$A$6:$B$4224,2,0) -> Ведущий специалист
A10: 9 | B10: Учетная запись | C10: agliullin.im | D10: ТЕКУЩИЙ ПЕРИОД | E10: Учетная запись ВКС | F10: 1249.63 | G10: 1 | H10: 28 | I10: 1249.63 | J10: 96.84 | K10: 100 | L10: 0 | M10: 1249.63 | P10: Аглиуллин Ильгиз Мазитович | Q10: agliullin.im@tc17.pp.gazprom-neft.ru | R10: =VLOOKUP(Таблица3[[#This Row],[Комментарий]],Справочник!$A$6:$B$4224,2,0) -> Специалист
A11: 10 | B11: Учетная запись | C11: adamanyuk.if | D11: ТЕКУЩИЙ ПЕРИОД | E11: Учетная запись ВКС | F11: 1249.63 | G11: 1 | H11: 28 | I11: 1249.63 | J11: 96.84 | K11: 100 | L11: 0 | M11: 1249.63 | P11: Адаманюк Инна Федоровна | Q11: adamanyuk.if@tc11.pp.gazprom-neft.ru | R11: =VLOOKUP(Таблица3[[#This Row],[Комментарий]],Справочник!$A$6:$B$4224,2,0) -> Главный специалист
A12: 11 | B12: Учетная запись | C12: adilov.ssh | D12: ТЕКУЩИЙ ПЕРИОД | E12: Учетная запись ВКС | F12: 1249.63 | G12: 1 | H12: 28 | I12: 1249.63 | J12: 96.84 | K12: 100 | L12: 0 | M12: 1249.63 | P12: Адилов Саидбек Шахсолтанович | Q12: adilov.ssh@tc15.pp.gazprom-neft.ru | R12: =VLOOKUP(Таблица3[[#This Row],[Комментарий]],Справочник!$A$6:$B$4224,2,0) -> Механик
A13: 12 | B13: Учетная запись | C13: adigezalov.an | D13: ТЕКУЩИЙ ПЕРИОД | E13: Учетная запись ВКС | F13: 1249.63 | G13: 1 | H13: 28 | I13: 1249.63 | J13: 96.84 | K13: 100 | L13: 0 | M13: 1249.63 | P13: Адыгезалов Ализаде Нуру Оглы | Q13: adigezalov.an@tc11.pp.gazprom-neft.ru | R13: =VLOOKUP(Таблица3[[#This Row],[Комментарий]],Справочник!$A$6:$B$4224,2,0) -> Начальник цеха
A14: 13 | B14: Учетная запись | C14: azarova.av | D14: ТЕКУЩИЙ ПЕРИОД | E14: Учетная запись ВКС | F14: 1249.63 | G14: 1 | H14: 28 | I14: 1249.63 | J14: 96.84 | K14: 100 | L14: 0 | M14: 1249.63 | P14: Азарова Алена Валерьевна | Q14: azarova.av@tc11.pp.gazprom-neft.ru | R14: =VLOOKUP(Таблица3[[#This Row],[Комментарий]],Справочник!$A$6:$B$4224,2,0) -> Ведущий специалист | S14: =[6]!ExtractElement(Таблица3[[#This Row],[Комментарий]],1," ") -> #NAME? | T14: =Таблица3[[#This Row],[Комментарий]] -> Азарова Алена Валерьевна
A15: 14 | B15: Учетная запись | C15: azyazov.da | D15: ТЕКУЩИЙ ПЕРИОД | E15: Учетная запись ВКС | F15: 1249.63 | G15: 1 | H15: 28 | I15: 1249.63 | J15: 96.84 | K15: 100 | L15: 0 | M15: 1249.63 | P15: Азязов Денис Александрович | Q15: azyazov.da@tc11.pp.gazprom-neft.ru | R15: =VLOOKUP(Таблица3[[#This Row],[Комментарий]],Справочник!$A$6:$B$4224,2,0) -> Руководитель направления нефтесервисных услуг и услуг общего профиля
A16: 15 | B16: Учетная запись | C16: ajnulin.rr | D16: ТЕКУЩИЙ ПЕРИОД | E16: Учетная запись ВКС | F16: 1249.63 | G16: 1 | H16: 28 | I16: 1249.63 | J16: 96.84 | K16: 100 | L16: 0 | M16: 1249.63 | P16: Айнулин Рустам Рашидович | Q16: ajnulin.rr@tc11.pp.gazprom-neft.ru | R16: =VLOOKUP(Таблица3[[#This Row],[Комментарий]],Справочник!$A$6:$B$4224,2,0) -> Главный сварщик
A17: 16 | B17: Учетная запись | C17: aytmukhametov.rr | D17: ТЕКУЩИЙ ПЕРИОД | E17: Учетная запись ВКС | F17: 1249.63 | G17: 1 | H17: 28 | I17: 1249.63 | J17: 96.84 | K17: 100 | L17: 0 | M17: 1249.63 | P17: Айтмухаметов Рамиль Раисович | Q17: aytmukhametov.rr@tc17.pp.gazprom-neft.ru | R17: =VLOOKUP(Таблица3[[#This Row],[Комментарий]],Справочник!$A$6:$B$4224,2,0) -> Мастер бр. № 8
A18: 17 | B18: Учетная запись | C18: akberdiev.bo | D18: ТЕКУЩИЙ ПЕРИОД | E18: Учетная запись ВКС | F18: 1249.63 | G18: 1 | H18: 28 | I18: 1249.63 | J18: 96.84 | K18: 100 | L18: 0 | M18: 1249.63 | P18: Акбердиев Булат Омурбекович | Q18: akberdiev.bo@tc15.pp.gazprom-neft.ru | R18: =VLOOKUP(Таблица3[[#This Row],[Комментарий]],Справочник!$A$6:$B$4224,2,0) -> Заместитель начальника цеха добычи и подготовки нефти
A19: 18 | B19: Учетная запись | C19: akzigitov.rs | D19: ТЕКУЩИЙ ПЕРИОД | E19: Учетная запись ВКС | F19: 1249.63 | G19: 1 | H19: 28 | I19: 1249.63 | J19: 96.84 | K19: 100 | L19: 0 | M19: 1249.63 | P19: Акзигитов Рафаэль Сайфуллович | Q19: akzigitov.rs@tc16.pp.gazprom-neft.ru | R19: =VLOOKUP(Таблица3[[#This Row],[Комментарий]],Справочник!$A$6:$B$4224,2,0) -> Мастер по ДНГиК бр.№9 ДНС-2 Ватинского м/р
A20: 19 | B20: Учетная запись | C20: aleksandrov.sv | D20: ТЕКУЩИЙ ПЕРИОД | E20: Учетная запись ВКС | F20: 1249.63 | G20: 1 | H20: 28 | I20: 1249.63 | J20: 96.84 | K20: 100 | L20: 0 | M20: 1249.63 | P20: Александров Сергей Валерьевич | Q20: aleksandrov.sv@tc17.pp.gazprom-neft.ru | R20: =VLOOKUP(Таблица3[[#This Row],[Комментарий]],Справочник!$A$6:$B$4224,2,0) -> Руководитель направления по производственной безопасности
A21: 20 | B21: Учетная запись | C21: alekhina.gv | D21: ТЕКУЩИЙ ПЕРИОД | E21: Учетная запись ВКС | F21: 1249.63 | G21: 1 | H21: 28 | I21: 1249.63 | J21: 96.84 | K21: 100 | L21: 0 | M21: 1249.63 | P21: Алехина Галина Владимировна | Q21: alekhina.gv@tc11.pp.gazprom-neft.ru | R21: =VLOOKUP(Таблица3[[#This Row],[Комментарий]],Справочник!$A$6:$B$4224,2,0) -> Техник
A22: 21 | B22: Учетная запись | C22: aleshina.ava | D22: ТЕКУЩИЙ ПЕРИОД | E22: Учетная запись ВКС | F22: 1249.63 | G22: 1 | H22: 28 | I22: 1249.63 | J22: 96.84 | K22: 100 | L22: 0 | M22: 1249.63 | P22: Алешина Алина Валентиновна | Q22: aleshina.ava@tc17.pp.gazprom-neft.ru | R22: =VLOOKUP(Таблица3[[#This Row],[Комментарий]],Справочник!$A$6:$B$4224,2,0) -> Ведущий специалист
A23: 22 | B23: Учетная запись | C23: aleshchenko.ip | D23: ТЕКУЩИЙ ПЕРИОД | E23: Учетная запись ВКС | F23: 1249.63 | G23: 1 | H23: 28 | I23: 1249.63 | J23: 96.84 | K23: 100 | L23: 0 | M23: 1249.63 | P23: Алещенко Иван Павлович | Q23: aleshchenko.ip@tc15.pp.gazprom-neft.ru | R23: =VLOOKUP(Таблица3[[#This Row],[Комментарий]],Справочник!$A$6:$B$4224,2,0) -> Руководитель направления по управлению данными
A24: 23 | B24: Учетная запись | C24: alipkachev.km | D24: ТЕКУЩИЙ ПЕРИОД | E24: Учетная запись ВКС | F24: 1249.63 | G24: 1 | H24: 28 | I24: 1249.63 | J24: 96.84 | K24: 100 | L24: 0 | M24: 1249.63 | P24: Алипкачев Казбек Магомедкамилович | Q24: alipkachev.km@tc14.pp.gazprom-neft.ru | R24: =VLOOKUP(Таблица3[[#This Row],[Комментарий]],Справочник!$A$6:$B$4224,2,0) -> Главный специалист
A25: 24 | B25: Учетная запись | C25: khabibullina.am | D25: ТЕКУЩИЙ ПЕРИОД | E25: Учетная запись ВКС | F25: 1249.63 | G25: 1 | H25: 28 | I25: 1249.63 | J25: 96.84 | K25: 100 | L25: 0 | M25: 1249.63 | P25: Хабибуллина Альмира Махияновна | Q25: khabibullina.am@tc11.pp.gazprom-neft.ru | R25: =VLOOKUP(Таблица3[[#This Row],[Комментарий]],Справочник!$A$6:$B$4224,2,0) -> Ведущий специалист
A26: 25 | B26: Учетная запись | C26: afanaseva.tr | D26: ТЕКУЩИЙ ПЕРИОД | E26: Учетная запись ВКС | F26: 1249.63 | G26: 1 | H26: 28 | I26: 1249.63 | J26: 96.84 | K26: 100 | L26: 0 | M26: 1249.63 | P26: Афанасьева Татьяна Рузилевна | Q26: afanaseva.tr@tc11.pp.gazprom-neft.ru | R26: =VLOOKUP(Таблица3[[#This Row],[Комментарий]],Справочник!$A$6:$B$4224,2,0) -> Руководитель направления по интеграции
... A29: 28 | B29: Учетная запись | C29: aldabirov.im | D29: ТЕКУЩИЙ ПЕРИОД | E29: Учетная запись ВКС | F29: 1249.63 | G29: 1 | H29: 28 | I29: 1249.63 | J29: 96.84 | K29: 100 | L29: 0 | M29: 1249.63 | P29: Альдабиров Ибрагим Мусаевич | Q29: aldabirov.im@tc7.pp.gazprom-neft.ru | R29: =VLOOKUP(Таблица3[[#This Row],[Комментарий]],Справочник!$A$6:$B$4224,2,0) -> Руководитель направления
A30: 29 | B30: Учетная запись | C30: alkhovik.ra | D30: ТЕКУЩИЙ ПЕРИОД | E30: Учетная запись ВКС | F30: 1249.63 | G30: 1 | H30: 28 | I30: 1249.63 | J30: 96.84 | K30: 100 | L30: 0 | M30: 1249.63 | P30: Альховик Руслан Анатольевич | Q30: alkhovik.ra@tc14.pp.gazprom-neft.ru | R30: =VLOOKUP(Таблица3[[#This Row],[Комментарий]],Справочник!$A$6:$B$4224,2,0) -> Старший механик | S30: =[6]!ExtractElement(Таблица3[[#This Row],[Комментарий]],1," ") -> #NAME? | T30: =Таблица3[[#This Row],[Комментарий]] -> Альховик Руслан Анатольевич
A31: 30 | B31: Учетная запись | C31: alkhovik.yuv | D31: ТЕКУЩИЙ ПЕРИОД | E31: Учетная запись ВКС | F31: 1249.63 | G31: 1 | H31: 28 | I31: 1249.63 | J31: 96.84 | K31: 100 | L31: 0 | M31: 1249.63 | P31: Альховик Юлия Валентиновна | Q31: alkhovik.yuv@tc20.pp.gazprom-neft.ru | R31: =VLOOKUP(Таблица3[[#This Row],[Комментарий]],Справочник!$A$6:$B$4224,2,0) -> Инженер по ООС
A32: 31 | B32: Учетная запись | C32: amineva.oa | D32: ТЕКУЩИЙ ПЕРИОД | E32: Учетная запись ВКС | F32: 1249.63 | G32: 1 | H32: 28 | I32: 1249.63 | J32: 96.84 | K32: 100 | L32: 0 | M32: 1249.63 | P32: Аминева Ольга Александровна | Q32: amineva.oa@tc14.pp.gazprom-neft.ru | R32: =VLOOKUP(Таблица3[[#This Row],[Комментарий]],Справочник!$A$6:$B$4224,2,0) -> Ведущий инженер
A33: 32 | B33: Учетная запись | C33: amirov.az | D33: ТЕКУЩИЙ ПЕРИОД | E33: Учетная запись ВКС | F33: 1249.63 | G33: 1 | H33: 28 | I33: 1249.63 | J33: 96.84 | K33: 100 | L33: 0 | M33: 1249.63 | P33: Амиров Артур Зинурович | Q33: #N/A | R33: =VLOOKUP(Таблица3[[#This Row],[Комментарий]],Справочник!$A$6:$B$4224,2,0) -> #N/A | S33: =VLOOKUP(Таблица3[[#This Row],[Комментарий]],[7]Лист_1!$H$2:$J$15000,3,0) -> #N/A | T33: уволен
A34: 33 | B34: Учетная запись | C34: ananin.in | D34: ТЕКУЩИЙ ПЕРИОД | E34: Учетная запись ВКС | F34: 1249.63 | G34: 1 | H34: 28 | I34: 1249.63 | J34: 96.84 | K34: 100 | L34: 0 | M34: 1249.63 | P34: Ананин Игорь Николаевич | Q34: ananin.in@tc15.pp.gazprom-neft.ru | R34: =VLOOKUP(Таблица3[[#This Row],[Комментарий]],Справочник!$A$6:$B$4224,2,0) -> Главный специалист
A35: 34 | B35: Учетная запись | C35: andieva.tf | D35: ТЕКУЩИЙ ПЕРИОД | E35: Учетная запись ВКС | F35: 1249.63 | G35: 1 | H35: 28 | I35: 1249.63 | J35: 96.84 | K35: 100 | L35: 0 | M35: 1249.63 | P35: Андиева Татьяна Федоровна | Q35: andieva.tf@tc8.pp.gazprom-neft.ru | R35: =VLOOKUP(Таблица3[[#This Row],[Комментарий]],Справочник!$A$6:$B$4224,2,0) -> Главный специалист
A36: 35 | B36: Учетная запись | C36: andreev.ayur | D36: ТЕКУЩИЙ ПЕРИОД | E36: Учетная запись ВКС | F36: 1249.63 | G36: 1 | H36: 28 | I36: 1249.63 | J36: 96.84 | K36: 100 | L36: 0 | M36: 1249.63 | P36: Андреев Александр Юрьевич | Q36: andreev.ayur@tc11.pp.gazprom-neft.ru | R36: =VLOOKUP(Таблица3[[#This Row],[Комментарий]],Справочник!$A$6:$B$4224,2,0) -> Руководитель проекта
A37: 36 | B37: Учетная запись | C37: andreev.aalek | D37: ТЕКУЩИЙ ПЕРИОД | E37: Учетная запись ВКС | F37: 1249.63 | G37: 1 | H37: 28 | I37: 1249.63 | J37: 96.84 | K37: 100 | L37: 0 | M37: 1249.63 | P37: Андреев Андрей Алексеевич | Q37: andreev.aalek@tc11.pp.gazprom-neft.ru | R37: =VLOOKUP(Таблица3[[#This Row],[Комментарий]],Справочник!$A$6:$B$4224,2,0) -> Главный специалист
A38: 37 | B38: Учетная запись | C38: andriyanova.ev | D38: ТЕКУЩИЙ ПЕРИОД | E38: Учетная запись ВКС | F38: 1249.63 | G38: 1 | H38: 28 | I38: 1249.63 | J38: 96.84 | K38: 100 | L38: 0 | M38: 1249.63 | P38: Андриянова Елена Викторовна | Q38: andriyanova.ev@tc18.pp.gazprom-neft.ru | R38: =VLOOKUP(Таблица3[[#This Row],[Комментарий]],Справочник!$A$6:$B$4224,2,0) -> Ведущий специалист | S38: =[6]!ExtractElement(Таблица3[[#This Row],[Комментарий]],1," ") -> #NAME? | T38: =Таблица3[[#This Row],[Комментарий]] -> Андриянова Елена Викторовна
A39: 38 | B39: Учетная запись | C39: andronov.av | D39: ТЕКУЩИЙ ПЕРИОД | E39: Учетная запись ВКС | F39: 1249.63 | G39: 1 | H39: 28 | I39: 1249.63 | J39: 96.84 | K39: 100 | L39: 0 | M39: 1249.63 | P39: Андронов Андрей Валентинович | Q39: andronov.av@tc6.pp.gazprom-neft.ru | R39: =VLOOKUP(Таблица3[[#This Row],[Комментарий]],Справочник!$A$6:$B$4224,2,0) -> Руководитель направления
A40: 39 | B40: Учетная запись | C40: androschuk.vv | D40: ТЕКУЩИЙ ПЕРИОД | E40: Учетная запись ВКС | F40: 1249.63 | G40: 1 | H40: 28 | I40: 1249.63 | J40: 96.84 | K40: 100 | L40: 0 | M40: 1249.63 | P40: Андрощук Василий Васильевич | Q40: androschuk.vv@tc21.pp.gazprom-neft.ru | R40: =VLOOKUP(Таблица3[[#This Row],[Комментарий]],Справочник!$A$6:$B$4224,2,0) -> Старший механик
A41: 40 | B41: Учетная запись | C41: andryushov.an | D41: ТЕКУЩИЙ ПЕРИОД | E41: Учетная запись ВКС | F41: 1249.63 | G41: 1 | H41: 28 | I41: 1249.63 | J41: 96.84 | K41: 100 | L41: 0 | M41: 1249.63 | P41: Андрюшов Андрей Николаевич | Q41: andryushov.an@tc12.pp.gazprom-neft.ru | R41: =VLOOKUP(Таблица3[[#This Row],[Комментарий]],Справочник!$A$6:$B$4224,2,0) -> Руководитель группы
A42: 41 | B42: Учетная запись | C42: anoshina.on | D42: ТЕКУЩИЙ ПЕРИОД | E42: Учетная запись ВКС | F42: 1249.63 | G42: 1 | H42: 28 | I42: 1249.63 | J42: 96.84 | K42: 100 | L42: 0 | M42: 1249.63 | P42: Аношина Ольга Николаевна | Q42: anoshina.on@tc7.pp.gazprom-neft.ru | R42: =VLOOKUP(Таблица3[[#This Row],[Комментарий]],Справочник!$A$6:$B$4224,2,0) -> Начальник отдела | S42: =[6]!ExtractElement(Таблица3[[#This Row],[Комментарий]],1," ") -> #NAME? | T42: =Таблица3[[#This Row],[Комментарий]] -> Аношина Ольга Николаевна
A43: 42 | B43: Учетная запись | C43: antonov.gg | D43: ТЕКУЩИЙ ПЕРИОД | E43: Учетная запись ВКС | F43: 1249.63 | G43: 1 | H43: 28 | I43: 1249.63 | J43: 96.84 | K43: 100 | L43: 0 | M43: 1249.63 | P43: Антонов Глеб Геннадьевич | Q43: antonov.gg@tc13.pp.gazprom-neft.ru | R43: =VLOOKUP(Таблица3[[#This Row],[Комментарий]],Справочник!$A$6:$B$4224,2,0) -> Главный специалист
A44: 43 | B44: Учетная запись | C44: antoshkina.tv | D44: ТЕКУЩИЙ ПЕРИОД | E44: Учетная запись ВКС | F44: 1249.63 | G44: 1 | H44: 28 | I44: 1249.63 | J44: 96.84 | K44: 100 | L44: 0 | M44: 1249.63 | P44: Антошкина Татьяна Васильевна | Q44: antoshkina.tv@tc11.pp.gazprom-neft.ru | R44: =VLOOKUP(Таблица3[[#This Row],[Комментарий]],Справочник!$A$6:$B$4224,2,0) -> Руководитель направления по аналитике
A45: 44 | B45: Учетная запись | C45: akhmadov.dr | D45: ТЕКУЩИЙ ПЕРИОД | E45: Учетная запись ВКС | F45: 1249.63 | G45: 1 | H45: 28 | I45: 1249.63 | J45: 96.84 | K45: 100 | L45: 0 | M45: 1249.63 | P45: Ахмадов Джабраил Русланович | Q45: akhmadov.dr@tc11.pp.gazprom-neft.ru | R45: =VLOOKUP(Таблица3[[#This Row],[Комментарий]],Справочник!$A$6:$B$4224,2,0) -> Ведущий инженер
A46: 45 | B46: Учетная запись | C46: apostolov.vv | D46: ТЕКУЩИЙ ПЕРИОД | E46: Учетная запись ВКС | F46: 1249.63 | G46: 1 | H46: 28 | I46: 1249.63 | J46: 96.84 | K46: 100 | L46: 0 | M46: 1249.63 | P46: Апостолов Василий Вадимович | Q46: apostolov.vv@tc6.pp.gazprom-neft.ru | R46: =VLOOKUP(Таблица3[[#This Row],[Комментарий]],Справочник!$A$6:$B$4224,2,0) -> Инженер-химик СИКН № 569 ПСП <Юган>
A47: 46 | B47: Учетная запись | C47: aranovskaya.yuv | D47: ТЕКУЩИЙ ПЕРИОД | E47: Учетная запись ВКС | F47: 1249.63 | G47: 1 | H47: 28 | I47: 1249.63 | J47: 96.84 | K47: 100 | L47: 0 | M47: 1249.63 | P47: Арановская Юлия Владимировна | Q47: aranovskaya.yuv@tc11.pp.gazprom-neft.ru | R47: =VLOOKUP(Таблица3[[#This Row],[Комментарий]],Справочник!$A$6:$B$4224,2,0) -> Специалист
A48: 47 | B48: Учетная запись | C48: akhmedov.khf | D48: ТЕКУЩИЙ ПЕРИОД | E48: Учетная запись ВКС | F48: 1249.63 | G48: 1 | H48: 28 | I48: 1249.63 | J48: 96.84 | K48: 100 | L48: 0 | M48: 1249.63 | P48: Ахмедов Хейбар Фамил Оглы | Q48: akhmedov.khf@tc11.pp.gazprom-neft.ru | R48: =VLOOKUP(Таблица3[[#This Row],[Комментарий]],Справочник!$A$6:$B$4224,2,0) -> #N/A
A49: 48 | B49: Учетная запись | C49: akhmedov.rb | D49: ТЕКУЩИЙ ПЕРИОД | E49: Учетная запись ВКС | F49: 1249.63 | G49: 1 | H49: 28 | I49: 1249.63 | J49: 96.84 | K49: 100 | L49: 0 | M49: 1249.63 | P49: Ахмедов Рауф Бахадур Оглы | Q49: akhmedov.rb@tc11.pp.gazprom-neft.ru | R49: =VLOOKUP(Таблица3[[#This Row],[Комментарий]],Справочник!$A$6:$B$4224,2,0) -> Заместитель начальника цеха
A50: 49 | B50: Учетная запись | C50: akhmedov.rsh | D50: ТЕКУЩИЙ ПЕРИОД | E50: Учетная запись ВКС | F50: 1249.63 | G50: 1 | H50: 28 | I50: 1249.63 | J50: 96.84 | K50: 100 | L50: 0 | M50: 1249.63 | P50: Ахмедов Рамин Шабанович | Q50: akhmedov.rsh@tc17.pp.gazprom-neft.ru | R50: =VLOOKUP(Таблица3[[#This Row],[Комментарий]],Справочник!$A$6:$B$4224,2,0) -> Мастер ДНС, КНС (Зап.-Ус.-Балыкского м/р)
A51: 50 | B51: Учетная запись | C51: akhmetgareev.si | D51: ТЕКУЩИЙ ПЕРИОД | E51: Учетная запись ВКС | F51: 1249.63 | G51: 1 | H51: 28 | I51: 1249.63 | J51: 96.84 | K51: 100 | L51: 0 | M51: 1249.63 | P51: Ахметгареев Сергей Иванович | Q51: akhmetgareev.si@tc12.pp.gazprom-neft.ru | R51: =VLOOKUP(Таблица3[[#This Row],[Комментарий]],Справочник!$A$6:$B$4224,2,0) -> Главный специалист
A52: 51 | B52: Учетная запись | C52: akhmetov.ami | D52: ТЕКУЩИЙ ПЕРИОД | E52: Учетная запись ВКС | F52: 1249.63 | G52: 1 | H52: 28 | I52: 1249.63 | J52: 96.84 | K52: 100 | L52: 0 | M52: 1249.63 | P52: Ахметов Айрат Минеразыевич | Q52: akhmetov.ami@tc11.pp.gazprom-neft.ru | R52: =VLOOKUP(Таблица3[[#This Row],[Комментарий]],Справочник!$A$6:$B$4224,2,0) -> Главный специалист
A53: 52 | B53: Учетная запись | C53: arkhangelskiy.gg | D53: ТЕКУЩИЙ ПЕРИОД | E53: Учетная запись ВКС | F53: 1249.63 | G53: 1 | H53: 28 | I53: 1249.63 | J53: 96.84 | K53: 100 | L53: 0 | M53: 1249.63 | P53: Архангельский Геннадий Геннадьевич | Q53: arkhangelskiy.gg@tc6.pp.gazprom-neft.ru | R53: =VLOOKUP(Таблица3[[#This Row],[Комментарий]],Справочник!$A$6:$B$4224,2,0) -> Ведущий специалист | S53: =[6]!ExtractElement(Таблица3[[#This Row],[Комментарий]],1," ") -> #NAME? | T53: =Таблица3[[#This Row],[Комментарий]] -> Архангельский Геннадий Геннадьевич
A54: 53 | B54: Учетная запись | C54: akhmetov.ik | D54: ТЕКУЩИЙ ПЕРИОД | E54: Учетная запись ВКС | F54: 1249.63 | G54: 1 | H54: 28 | I54: 1249.63 | J54: 96.84 | K54: 100 | L54: 0 | M54: 1249.63 | P54: Ахметов Ильдар Халафович | Q54: akhmetov.ik@tc16.pp.gazprom-neft.ru | R54: =VLOOKUP(Таблица3[[#This Row],[Комментарий]],Справочник!$A$6:$B$4224,2,0) -> Мастер ПиСН по обслуживанию ДНС-1, КНС-1 бр. № 17 Ватинское м/р
A55: 54 | B55: Учетная запись | C55: arkhipov.ap | D55: ТЕКУЩИЙ ПЕРИОД | E55: Учетная запись ВКС | F55: 1249.63 | G55: 1 | H55: 28 | I55: 1249.63 | J55: 96.84 | K55: 100 | L55: 0 | M55: 1249.63 | P55: Архипов Александр Петрович | Q55: arkhipov.ap@tc11.pp.gazprom-neft.ru | R55: =VLOOKUP(Таблица3[[#This Row],[Комментарий]],Справочник!$A$6:$B$4224,2,0) -> Заместитель начальника отдела
A56: 55 | B56: Учетная запись | C56: akhmetov.rri | D56: ТЕКУЩИЙ ПЕРИОД | E56: Учетная запись ВКС | F56: 1249.63 | G56: 1 | H56: 28 | I56: 1249.63 | J56: 96.84 | K56: 100 | L56: 0 | M56: 1249.63 | P56: Ахметов Рузиль Ринатович | Q56: akhmetov.rri@tc7.pp.gazprom-neft.ru | R56: =VLOOKUP(Таблица3[[#This Row],[Комментарий]],Справочник!$A$6:$B$4224,2,0) -> Ведущий инженер
A57: 56 | B57: Учетная запись | C57: astanov.aa | D57: ТЕКУЩИЙ ПЕРИОД | E57: Учетная запись ВКС | F57: 1249.63 | G57: 1 | H57: 28 | I57: 1249.63 | J57: 96.84 | K57: 100 | L57: 0 | M57: 1249.63 | P57: Астанов Анар Аливерди Оглы | Q57: astanov.aa@tc6.pp.gazprom-neft.ru | R57: =VLOOKUP(Таблица3[[#This Row],[Комментарий]],Справочник!$A$6:$B$4224,2,0) -> #N/A
A58: 57 | B58: Учетная запись | C58: akhmetzyanov.an | D58: ТЕКУЩИЙ ПЕРИОД | E58: Учетная запись ВКС | F58: 1249.63 | G58: 1 | H58: 28 | I58: 1249.63 | J58: 96.84 | K58: 100 | L58: 0 | M58: 1249.63 | P58: Ахметзянов Альберт Назимович | Q58: akhmetzyanov.an@tc6.pp.gazprom-neft.ru | R58: =VLOOKUP(Таблица3[[#This Row],[Комментарий]],Справочник!$A$6:$B$4224,2,0) -> Руководитель направления
A59: 58 | B59: Учетная запись | C59: ataeva.iv | D59: ТЕКУЩИЙ ПЕРИОД | E59: Учетная запись ВКС | F59: 1249.63 | G59: 1 | H59: 28 | I59: 1249.63 | J59: 96.84 | K59: 100 | L59: 0 | M59: 1249.63 | P59: Атаева Ирина Вакосовна | Q59: ataeva.iv@tc18.pp.gazprom-neft.ru | R59: =VLOOKUP(Таблица3[[#This Row],[Комментарий]],Справочник!$A$6:$B$4224,2,0) -> Ведущий специалист по сопровождению договорных документов
A60: 59 | B60: Учетная запись | C60: atamanenko.ae | D60: ТЕКУЩИЙ ПЕРИОД | E60: Учетная запись ВКС | F60: 1249.63 | G60: 1 | H60: 28 | I60: 1249.63 | J60: 96.84 | K60: 100 | L60: 0 | M60: 1249.63 | P60: Атаманенко Александр Евгеньевич | Q60: atamanenko.ae@tc12.pp.gazprom-neft.ru | R60: =VLOOKUP(Таблица3[[#This Row],[Комментарий]],Справочник!$A$6:$B$4224,2,0) -> Руководитель направления по планированию и прогнозированию
A61: 60 | B61: Учетная запись | C61: akhmetzyanov.nm | D61: ТЕКУЩИЙ ПЕРИОД | E61: Учетная запись ВКС | F61: 1249.63 | G61: 1 | H61: 28 | I61: 1249.63 | J61: 96.84 | K61: 100 | L61: 0 | M61: 1249.63 | P61: Ахметзянов Наиль Мажитович | Q61: akhmetzyanov.nm@tc11.pp.gazprom-neft.ru | R61: =VLOOKUP(Таблица3[[#This Row],[Комментарий]],Справочник!$A$6:$B$4224,2,0) -> Главный специалист
A62: 61 | B62: Учетная запись | C62: akhmetzyanov.rm | D62: ТЕКУЩИЙ ПЕРИОД | E62: Учетная запись ВКС | F62: 1249.63 | G62: 1 | H62: 28 | I62: 1249.63 | J62: 96.84 | K62: 100 | L62: 0 | M62: 1249.63 | P62: Ахметзянов Руслан Мажитович | Q62: akhmetzyanov.rm@tc11.pp.gazprom-neft.ru | R62: =VLOOKUP(Таблица3[[#This Row],[Комментарий]],Справочник!$A$6:$B$4224,2,0) -> Главный специалист
A63: 62 | B63: Учетная запись | C63: akhverdiev.ka | D63: ТЕКУЩИЙ ПЕРИОД | E63: Учетная запись ВКС | F63: 1249.63 | G63: 1 | H63: 28 | I63: 1249.63 | J63: 96.84 | K63: 100 | L63: 0 | M63: 1249.63 | P63: Ахвердиев Камил Али оглы | Q63: akhverdiev.ka@tc21.pp.gazprom-neft.ru | R63: =VLOOKUP(Таблица3[[#This Row],[Комментарий]],Справочник!$A$6:$B$4224,2,0) -> Главный специалист
A64: 63 | B64: Учетная запись | C64: ayupov.ush | D64: ТЕКУЩИЙ ПЕРИОД | E64: Учетная запись ВКС | F64: 1249.63 | G64: 1 | H64: 28 | I64: 1249.63 | J64: 96.84 | K64: 100 | L64: 0 | M64: 1249.63 | P64: Аюпов Урал Шарифович | Q64: ayupov.ush@tc7.pp.gazprom-neft.ru | R64: =VLOOKUP(Таблица3[[#This Row],[Комментарий]],Справочник!$A$6:$B$4224,2,0) -> Главный специалист
A65: 64 | B65: Учетная запись | C65: babaev.pi | D65: ТЕКУЩИЙ ПЕРИОД | E65: Учетная запись ВКС | F65: 1249.63 | G65: 1 | H65: 28 | I65: 1249.63 | J65: 96.84 | K65: 100 | L65: 0 | M65: 1249.63 | P65: Бабаев Павел Исидорович | Q65: babaev.pi@tc18.pp.gazprom-neft.ru | R65: =VLOOKUP(Таблица3[[#This Row],[Комментарий]],Справочник!$A$6:$B$4224,2,0) -> Начальник смены
... A74: 73 | B74: Учетная запись | C74: balakin.em | D74: ТЕКУЩИЙ ПЕРИОД | E74: Учетная запись ВКС | F74: 1249.63 | G74: 1 | H74: 28 | I74: 1249.63 | J74: 96.84 | K74: 100 | L74: 0 | M74: 1249.63 | P74: Балакин Евгений Михайлович | Q74: balakin.em@tc11.pp.gazprom-neft.ru | R74: =VLOOKUP(Таблица3[[#This Row],[Комментарий]],Справочник!$A$6:$B$4224,2,0) -> Главный специалист по охране труда
A75: 74 | B75: Учетная запись | C75: balandina.aa | D75: ТЕКУЩИЙ ПЕРИОД | E75: Учетная запись ВКС | F75: 1249.63 | G75: 1 | H75: 28 | I75: 1249.63 | J75: 96.84 | K75: 100 | L75: 0 | M75: 1249.63 | P75: Баландина Анастасия Анатольевна | Q75: balandina.aa@tc11.pp.gazprom-neft.ru | R75: =VLOOKUP(Таблица3[[#This Row],[Комментарий]],Справочник!$A$6:$B$4224,2,0) -> Начальник отдела | S75: =[6]!ExtractElement(Таблица3[[#This Row],[Комментарий]],1," ") -> #NAME? | T75: =Таблица3[[#This Row],[Комментарий]] -> Баландина Анастасия Анатольевна
A76: 75 | B76: Учетная запись | C76: balatsenko.an | D76: ТЕКУЩИЙ ПЕРИОД | E76: Учетная запись ВКС | F76: 1249.63 | G76: 1 | H76: 28 | I76: 1249.63 | J76: 96.84 | K76: 100 | L76: 0 | M76: 1249.63 | P76: Балаценко Алексей Николаевич | Q76: balatsenko.an@tc14.pp.gazprom-neft.ru | R76: =VLOOKUP(Таблица3[[#This Row],[Комментарий]],Справочник!$A$6:$B$4224,2,0) -> Руководитель направления по СМАРТ-сервису
A77: 76 | B77: Учетная запись | C77: balmasov.oa | D77: ТЕКУЩИЙ ПЕРИОД | E77: Учетная запись ВКС | F77: 1249.63 | G77: 1 | H77: 28 | I77: 1249.63 | J77: 96.84 | K77: 100 | L77: 0 | M77: 1249.63 | P77: Балмасов Олег Александрович | Q77: balmasov.oa@tc11.pp.gazprom-neft.ru | R77: =VLOOKUP(Таблица3[[#This Row],[Комментарий]],Справочник!$A$6:$B$4224,2,0) -> Руководитель проекта
A78: 77 | B78: Учетная запись | C78: balmich.sv | D78: ТЕКУЩИЙ ПЕРИОД | E78: Учетная запись ВКС | F78: 1249.63 | G78: 1 | H78: 28 | I78: 1249.63 | J78: 96.84 | K78: 100 | L78: 0 | M78: 1249.63 | P78: Бальмич Сергей Владимирович | Q78: balmich.sv@tc13.pp.gazprom-neft.ru | R78: =VLOOKUP(Таблица3[[#This Row],[Комментарий]],Справочник!$A$6:$B$4224,2,0) -> Начальник установки
A79: 78 | B79: Учетная запись | C79: balchugova.ks | D79: ТЕКУЩИЙ ПЕРИОД | E79: Учетная запись ВКС | F79: 1249.63 | G79: 1 | H79: 28 | I79: 1249.63 | J79: 96.84 | K79: 100 | L79: 0 | M79: 1249.63 | P79: Бальчугова Катерина Сергеевна | Q79: balchugova.ks@tc11.pp.gazprom-neft.ru | R79: =VLOOKUP(Таблица3[[#This Row],[Комментарий]],Справочник!$A$6:$B$4224,2,0) -> Ведущий специалист
A80: 79 | B80: Учетная запись | C80: balyagutdinova.yi | D80: ТЕКУЩИЙ ПЕРИОД | E80: Учетная запись ВКС | F80: 1249.63 | G80: 1 | H80: 28 | I80: 1249.63 | J80: 96.84 | K80: 100 | L80: 0 | M80: 1249.63 | P80: Балягутдинова Юлия Ибрагимовна | Q80: balyagutdinova.yi@tc11.pp.gazprom-neft.ru | R80: =VLOOKUP(Таблица3[[#This Row],[Комментарий]],Справочник!$A$6:$B$4224,2,0) -> Инженер-химик СИКН № 1502 ПСП <Славнефть>
A81: 80 | B81: Учетная запись | C81: banket.vv | D81: ТЕКУЩИЙ ПЕРИОД | E81: Учетная запись ВКС | F81: 1249.63 | G81: 1 | H81: 28 | I81: 1249.63 | J81: 96.84 | K81: 100 | L81: 0 | M81: 1249.63 | P81: Банкет Виктор Владимирович | Q81: banket.vv@tc18.pp.gazprom-neft.ru | R81: =VLOOKUP(Таблица3[[#This Row],[Комментарий]],Справочник!$A$6:$B$4224,2,0) -> Начальник участка
A82: 81 | B82: Учетная запись | C82: barzul.vv | D82: ТЕКУЩИЙ ПЕРИОД | E82: Учетная запись ВКС | F82: 1249.63 | G82: 1 | H82: 28 | I82: 1249.63 | J82: 96.84 | K82: 100 | L82: 0 | M82: 1249.63 | P82: Барзул Василий Васильевич | Q82: barzul.vv@tc11.pp.gazprom-neft.ru | R82: =VLOOKUP(Таблица3[[#This Row],[Комментарий]],Справочник!$A$6:$B$4224,2,0) -> Руководитель программ
A83: 82 | B83: Учетная запись | C83: barinov.aa | D83: ТЕКУЩИЙ ПЕРИОД | E83: Учетная запись ВКС | F83: 1249.63 | G83: 1 | H83: 28 | I83: 1249.63 | J83: 96.84 | K83: 100 | L83: 0 | M83: 1249.63 | P83: Баринов Александр Александрович | Q83: barinov.aa@tc7.pp.gazprom-neft.ru | R83: =VLOOKUP(Таблица3[[#This Row],[Комментарий]],Справочник!$A$6:$B$4224,2,0) -> Генеральный директор
A84: 83 | B84: Учетная запись | C84: barnash.rv | D84: ТЕКУЩИЙ ПЕРИОД | E84: Учетная запись ВКС | F84: 1249.63 | G84: 1 | H84: 28 | I84: 1249.63 | J84: 96.84 | K84: 100 | L84: 0 | M84: 1249.63 | P84: Барнаш Рената Владимировна | Q84: barnash.rv@tc6.pp.gazprom-neft.ru | R84: =VLOOKUP(Таблица3[[#This Row],[Комментарий]],Справочник!$A$6:$B$4224,2,0) -> Специалист по содержанию социально-бытовых объектов
A85: 84 | B85: Учетная запись | C85: barsukov.ay | D85: ТЕКУЩИЙ ПЕРИОД | E85: Учетная запись ВКС | F85: 1249.63 | G85: 1 | H85: 28 | I85: 1249.63 | J85: 96.84 | K85: 100 | L85: 0 | M85: 1249.63 | P85: Барсуков Алексей Юрьевич | Q85: barsukov.ay@tc12.pp.gazprom-neft.ru | R85: =VLOOKUP(Таблица3[[#This Row],[Комментарий]],Справочник!$A$6:$B$4224,2,0) -> Руководитель направления по освоению скважин после бурения
A86: 85 | B86: Учетная запись | C86: baryshev.vvya | D86: ТЕКУЩИЙ ПЕРИОД | E86: Учетная запись ВКС | F86: 1249.63 | G86: 1 | H86: 28 | I86: 1249.63 | J86: 96.84 | K86: 100 | L86: 0 | M86: 1249.63 | P86: Барышев Владимир Вячеславович | Q86: baryshev.vvya@tc11.pp.gazprom-neft.ru | R86: =VLOOKUP(Таблица3[[#This Row],[Комментарий]],Справочник!$A$6:$B$4224,2,0) -> Старший механик (АБК ЦППН-1)
A87: 86 | B87: Учетная запись | C87: baryshev.sa | D87: ТЕКУЩИЙ ПЕРИОД | E87: Учетная запись ВКС | F87: 1249.63 | G87: 1 | H87: 28 | I87: 1249.63 | J87: 96.84 | K87: 100 | L87: 0 | M87: 1249.63 | P87: Барышев Сергей Александрович | Q87: baryshev.sa@tc14.pp.gazprom-neft.ru | R87: =VLOOKUP(Таблица3[[#This Row],[Комментарий]],Справочник!$A$6:$B$4224,2,0) -> Технолог сменный
... A89: 88 | B89: Учетная запись | C89: batygin.iv | D89: ТЕКУЩИЙ ПЕРИОД | E89: Учетная запись ВКС | F89: 1249.63 | G89: 1 | H89: 28 | I89: 1249.63 | J89: 96.84 | K89: 100 | L89: 0 | M89: 1249.63 | P89: Батыгин Игорь Владимирович | Q89: batygin.iv@tc11.pp.gazprom-neft.ru | R89: =VLOOKUP(Таблица3[[#This Row],[Комментарий]],Справочник!$A$6:$B$4224,2,0) -> Главный специалист
A90: 89 | B90: Учетная запись | C90: batkov.yo | D90: ТЕКУЩИЙ ПЕРИОД | E90: Учетная запись ВКС | F90: 1249.63 | G90: 1 | H90: 28 | I90: 1249.63 | J90: 96.84 | K90: 100 | L90: 0 | M90: 1249.63 | P90: Батьков Ярослав Олегович | Q90: #N/A | R90: =VLOOKUP(Таблица3[[#This Row],[Комментарий]],Справочник!$A$6:$B$4224,2,0) -> #N/A | S90: =VLOOKUP(Таблица3[[#This Row],[Комментарий]],[7]Лист_1!$H$2:$J$15000,3,0) -> #N/A | T90: уволен
A91: 90 | B91: Учетная запись | C91: bakhtiyarov.ga | D91: ТЕКУЩИЙ ПЕРИОД | E91: Учетная запись ВКС | F91: 1249.63 | G91: 1 | H91: 28 | I91: 1249.63 | J91: 96.84 | K91: 100 | L91: 0 | M91: 1249.63 | P91: Бахтияров Георгий Алексеевич | Q91: bakhtiyarov.ga@tc14.pp.gazprom-neft.ru | R91: =VLOOKUP(Таблица3[[#This Row],[Комментарий]],Справочник!$A$6:$B$4224,2,0) -> Главный специалист
A92: 91 | B92: Учетная запись | C92: bashkova.tyu | D92: ТЕКУЩИЙ ПЕРИОД | E92: Учетная запись ВКС | F92: 1249.63 | G92: 1 | H92: 28 | I92: 1249.63 | J92: 96.84 | K92: 100 | L92: 0 | M92: 1249.63 | P92: Башкова Татьяна Юрьевна | Q92: bashkova.tyu@tc6.pp.gazprom-neft.ru | R92: =VLOOKUP(Таблица3[[#This Row],[Комментарий]],Справочник!$A$6:$B$4224,2,0) -> Ведущий инженер
A93: 92 | B93: Учетная запись | C93: bezuglaya.es | D93: ТЕКУЩИЙ ПЕРИОД | E93: Учетная запись ВКС | F93: 1249.63 | G93: 1 | H93: 28 | I93: 1249.63 | J93: 96.84 | K93: 100 | L93: 0 | M93: 1249.63 | P93: Безуглая Елена Сергеевна | Q93: bezuglaya.es@tc19.pp.gazprom-neft.ru | R93: =VLOOKUP(Таблица3[[#This Row],[Комментарий]],Справочник!$A$6:$B$4224,2,0) -> Мастер
A94: 93 | B94: Учетная запись | C94: bezuglyy.dv | D94: ТЕКУЩИЙ ПЕРИОД | E94: Учетная запись ВКС | F94: 1249.63 | G94: 1 | H94: 28 | I94: 1249.63 | J94: 96.84 | K94: 100 | L94: 0 | M94: 1249.63 | P94: Безуглый Денис Владимирович | Q94: bezuglyy.dv@tc11.pp.gazprom-neft.ru | R94: =VLOOKUP(Таблица3[[#This Row],[Комментарий]],Справочник!$A$6:$B$4224,2,0) -> Главный специалист
A95: 94 | B95: Учетная запись | C95: beybutov.sho | D95: ТЕКУЩИЙ ПЕРИОД | E95: Учетная запись ВКС | F95: 1249.63 | G95: 1 | H95: 28 | I95: 1249.63 | J95: 96.84 | K95: 100 | L95: 0 | M95: 1249.63 | P95: Бейбутов Ширин-Буба Октябрович | Q95: beybutov.sho@tc19.pp.gazprom-neft.ru | R95: =VLOOKUP(Таблица3[[#This Row],[Комментарий]],Справочник!$A$6:$B$4224,2,0) -> Мастер Тайлаковского м/р
A96: 95 | B96: Учетная запись | C96: belan.ea | D96: ТЕКУЩИЙ ПЕРИОД | E96: Учетная запись ВКС | F96: 1249.63 | G96: 1 | H96: 28 | I96: 1249.63 | J96: 96.84 | K96: 100 | L96: 0 | M96: 1249.63 | P96: Белан Екатерина Александровна | Q96: belan.ea@tc16.pp.gazprom-neft.ru | R96: =VLOOKUP(Таблица3[[#This Row],[Комментарий]],Справочник!$A$6:$B$4224,2,0) -> Мастер ПиСН по обслуживанию ДНС-3, КНС-6, 6а, 6б бр. № 19 Ватинское м/р
A97: 96 | B97: Учетная запись | C97: belan.si | D97: ТЕКУЩИЙ ПЕРИОД | E97: Учетная запись ВКС | F97: 1249.63 | G97: 1 | H97: 28 | I97: 1249.63 | J97: 96.84 | K97: 100 | L97: 0 | M97: 1249.63 | P97: Белан Светлана Ивановна | Q97: belan.si@tc14.pp.gazprom-neft.ru | R97: =VLOOKUP(Таблица3[[#This Row],[Комментарий]],Справочник!$A$6:$B$4224,2,0) -> Главный специалист
A98: 97 | B98: Учетная запись | C98: belikova.av | D98: ТЕКУЩИЙ ПЕРИОД | E98: Учетная запись ВКС | F98: 1249.63 | G98: 1 | H98: 28 | I98: 1249.63 | J98: 96.84 | K98: 100 | L98: 0 | M98: 1249.63 | P98: Беликова Алена Викторовна | Q98: belikova.av@tc6.pp.gazprom-neft.ru | R98: =VLOOKUP(Таблица3[[#This Row],[Комментарий]],Справочник!$A$6:$B$4224,2,0) -> Главный специалист | S98: =[6]!ExtractElement(Таблица3[[#This Row],[Комментарий]],1," ") -> #NAME? | T98: =Таблица3[[#This Row],[Комментарий]] -> Беликова Алена Викторовна
A99: 98 | B99: Учетная запись | C99: belikova.em | D99: ТЕКУЩИЙ ПЕРИОД | E99: Учетная запись ВКС | F99: 1249.63 | G99: 1 | H99: 28 | I99: 1249.63 | J99: 96.84 | K99: 100 | L99: 0 | M99: 1249.63 | P99: Беликова Екатерина Михайловна | Q99: belikova.em@tc15.pp.gazprom-neft.ru | R99: =VLOOKUP(Таблица3[[#This Row],[Комментарий]],Справочник!$A$6:$B$4224,2,0) -> Главный специалист
A100: 99 | B100: Учетная запись | C100: belous.nv | D100: ТЕКУЩИЙ ПЕРИОД | E100: Учетная запись ВКС | F100: 1249.63 | G100: 1 | H100: 28 | I100: 1249.63 | J100: 96.84 | K100: 100 | L100: 0 | M100: 1249.63 | P100: Белоус Наталья Васильевна | Q100: belous.nv@tc11.pp.gazprom-neft.ru | R100: =VLOOKUP(Таблица3[[#This Row],[Комментарий]],Справочник!$A$6:$B$4224,2,0) -> Начальник отдела
A101: 100 | B101: Учетная запись | C101: beltoev.sa | D101: ТЕКУЩИЙ ПЕРИОД | E101: Учетная запись ВКС | F101: 1249.63 | G101: 1 | H101: 28 | I101: 1249.63 | J101: 96.84 | K101: 100 | L101: 0 | M101: 1249.63 | P101: Бельтоев Сулейман Абубакарович | Q101: beltoev.sa@tc15.pp.gazprom-neft.ru | R101: =VLOOKUP(Таблица3[[#This Row],[Комментарий]],Справочник!$A$6:$B$4224,2,0) -> Мастер
A102: 101 | B102: Учетная запись | C102: berdinskikh.av | D102: ТЕКУЩИЙ ПЕРИОД | E102: Учетная запись ВКС | F102: 1249.63 | G102: 1 | H102: 28 | I102: 1249.63 | J102: 96.84 | K102: 100 | L102: 0 | M102: 1249.63 | P102: Бердинских Алексей Валерьевич | Q102: berdinskikh.av@tc13.pp.gazprom-neft.ru | R102: =VLOOKUP(Таблица3[[#This Row],[Комментарий]],Справочник!$A$6:$B$4224,2,0) -> Главный специалист
A103: 102 | B103: Учетная запись | C103: beregoy.gi | D103: ТЕКУЩИЙ ПЕРИОД | E103: Учетная запись ВКС | F103: 1249.63 | G103: 1 | H103: 28 | I103: 1249.63 | J103: 96.84 | K103: 100 | L103: 0 | M103: 1249.63 | P103: Берегой Григорий Иванович | Q103: beregoy.gi@tc11.pp.gazprom-neft.ru | R103: =VLOOKUP(Таблица3[[#This Row],[Комментарий]],Справочник!$A$6:$B$4224,2,0) -> Главный специалист
A104: 103 | B104: Учетная запись | C104: berezhnoj.dv | D104: ТЕКУЩИЙ ПЕРИОД | E104: Учетная запись ВКС | F104: 1249.63 | G104: 1 | H104: 28 | I104: 1249.63 | J104: 96.84 | K104: 100 | L104: 0 | M104: 1249.63 | P104: Бережной Денис Владимирович | Q104: berezhnoj.dv@tc7.pp.gazprom-neft.ru | R104: =VLOOKUP(Таблица3[[#This Row],[Комментарий]],Справочник!$A$6:$B$4224,2,0) -> Руководитель по планированию и обеспечению ресурсами
A105: 104 | B105: Учетная запись | C105: berezina.aan | D105: ТЕКУЩИЙ ПЕРИОД | E105: Учетная запись ВКС | F105: 1249.63 | G105: 1 | H105: 28 | I105: 1249.63 | J105: 96.84 | K105: 100 | L105: 0 | M105: 1249.63 | P105: Березина Алина Андреевна | Q105: berezina.aan@tc11.pp.gazprom-neft.ru | R105: =VLOOKUP(Таблица3[[#This Row],[Комментарий]],Справочник!$A$6:$B$4224,2,0) -> Главный специалист
A106: 105 | B106: Учетная запись | C106: bessonov.in | D106: ТЕКУЩИЙ ПЕРИОД | E106: Учетная запись ВКС | F106: 1249.63 | G106: 1 | H106: 28 | I106: 1249.63 | J106: 96.84 | K106: 100 | L106: 0 | M106: 1249.63 | P106: Бессонов Иван Николаевич | Q106: bessonov.in@tc13.pp.gazprom-neft.ru | R106: =VLOOKUP(Таблица3[[#This Row],[Комментарий]],Справочник!$A$6:$B$4224,2,0) -> Мастер ПиСН по обслуживанию ДНС-2, КНС-8 бр. № 18 Ватинское м/р
A107: 106 | B107: Учетная запись | C107: bessonova.in | D107: ТЕКУЩИЙ ПЕРИОД | E107: Учетная запись ВКС | F107: 1249.63 | G107: 1 | H107: 28 | I107: 1249.63 | J107: 96.84 | K107: 100 | L107: 0 | M107: 1249.63 | P107: Бессонова Ирина Николаевна | Q107: bessonova.in@tc11.pp.gazprom-neft.ru | R107: =VLOOKUP(Таблица3[[#This Row],[Комментарий]],Справочник!$A$6:$B$4224,2,0) -> Начальник управления
A108: 107 | B108: Учетная запись | C108: bets.ei | D108: ТЕКУЩИЙ ПЕРИОД | E108: Учетная запись ВКС | F108: 1249.63 | G108: 1 | H108: 28 | I108: 1249.63 | J108: 96.84 | K108: 100 | L108: 0 | M108: 1249.63 | P108: Бец Эдуард Иванович | Q108: bets.ei@tc7.pp.gazprom-neft.ru | R108: =VLOOKUP(Таблица3[[#This Row],[Комментарий]],Справочник!$A$6:$B$4224,2,0) -> Главный специалист
A109: 108 | B109: Учетная запись | C109: bilyj.nv | D109: ТЕКУЩИЙ ПЕРИОД | E109: Учетная запись ВКС | F109: 1249.63 | G109: 1 | H109: 28 | I109: 1249.63 | J109: 96.84 | K109: 100 | L109: 0 | M109: 1249.63 | P109: Билый Николай Васильевич | Q109: bilyj.nv@tc11.pp.gazprom-neft.ru | R109: =VLOOKUP(Таблица3[[#This Row],[Комментарий]],Справочник!$A$6:$B$4224,2,0) -> Начальник отдела
A110: 1054 | B110: Учетная запись | C110: bikieva.oa | D110: ТЕКУЩИЙ ПЕРИОД | E110: Учетная запись ВКС | F110: 1249.63 | G110: 1 | H110: 28 | I110: 1249.63 | J110: 96.84 | K110: 100 | L110: 0 | M110: 1249.63 | P110: Бикиева Ольга Алексеевна | Q110: bilkin.vn@tc11.pp.gazprom-neft.ru | R110: =VLOOKUP(Таблица3[[#This Row],[Комментарий]],Справочник!$A$6:$B$4224,2,0) -> #N/A | S110: =VLOOKUP(Таблица3[[#This Row],[Комментарий]],[7]Лист_1!$H$2:$J$15000,3,0) -> #N/A
A111: 110 | B111: Учетная запись | C111: biryukov.syu | D111: ТЕКУЩИЙ ПЕРИОД | E111: Учетная запись ВКС | F111: 1249.63 | G111: 1 | H111: 28 | I111: 1249.63 | J111: 96.84 | K111: 100 | L111: 0 | M111: 1249.63 | P111: Бирюков Станислав Юрьевич | Q111: biryukov.syu@tc15.pp.gazprom-neft.ru | R111: =VLOOKUP(Таблица3[[#This Row],[Комментарий]],Справочник!$A$6:$B$4224,2,0) -> Ведущий специалист
...
